Workbook

Sheet PH-Phases
A1: Phase ID | B1: Phase Name | C1: Summary | D1: Goals | E1: Objectives
A2: PH-01 | B2: Full Conversion (Decision-Centric Core) | C2: Deliver the core decision engine for contract-first ordering, pricing enforcement, and rule-driven fulfillment to replace spreadsheets and tribal knowledge. | D2: Enforce contracts and pricing at order time; Execute compliant fulfillment without manual interpretation | E2: Orders are created with correct pricing and terms on first pass; Manual contract validation is eliminated for standard orders; Pricing, approval, and substitution decisions are fully auditable
A3: PH-02 | B3: Automation (Operational Scale) | C3: Automate exception handling, approvals, and multi-source fulfillment to increase throughput and reduce operational firefighting. | D3: Reduce operational escalations and manual intervention; Increase order throughput without additional headcount | E3: Majority of orders process without manual escalation; Automated approvals handle most margin and compliance thresholds; Fulfillment routing executes consistently across warehouses
A4: PH-03 | B4: Scale (Predictability & Expansion) | C4: Extend the OMS to support new warehouses, vendors, regulations, and analytics with confidence and predictable financial outcomes. | D4: Enable rapid expansion without increasing compliance or margin risk; Improve forecasting accuracy and financial predictability | E4: New warehouses and vendors onboard with minimal configuration effort; Demand, margin, and service-level forecasting is reliable; Audit readiness is achieved without manual reconciliation

Sheet DEL-Deliverables
A1: Deliverable ID | B1: Strategy Ref | C1: Blueprint Ref | D1: Phase Ref ID | E1: Requirement Type | F1: Deliverable Name | G1: Deliverable Description | H1: Notes | I1: Complexity | J1: Effort | K1: Hours | L1: Epic Roll-Up | M1: ELI Roll-Up
A2: DEL-001 | B2: CAP-001 | C2: BP-1765865704672 | D2: PH-01 | E2: Experience | F2: Contract Management | G2: Manage customer profiles, contracts, service terms, and compliance requirements so orders are evaluated against the correct agreements and constraints. | I2: Medium | J2: 8 | K2: 120 | L2: 3 | M2: 9
A3: DEL-002 | B3: CAP-002 | C3: BP-1765865704672 | D3: PH-01 | E3: Experience | F3: Inventory Management | G3: Provide real-time visibility and control over inventory across warehouses and vendor sources to support accurate sourcing, allocation, and fulfillment decisions. | I3: Medium | J3: 8 | K3: 120 | L3: 3 | M3: 9
A4: DEL-003 | B4: CAP-003 | C4: BP-1765865704672 | D4: PH-01 | E4: Experience | F4: Order Management | G4: Create, validate, and manage sales orders with contract-first pricing and controlled lifecycle changes enforced at order time. | I4: High | J4: 13 | K4: 160 | L4: 4 | M4: 12
A5: DEL-004 | B5: CAP-004 | C5: BP-1765865704672 | D5: PH-01 | E5: Experience | F5: Fulfillment Orchestration | G5: Orchestrate compliant, rule-driven fulfillment across warehouses and vendors by applying rules for splits, substitutions, and service levels. | I5: High | J5: 13 | K5: 160 | L5: 3 | M5: 9
A6: DEL-005 | B6: CAP-005 | C6: BP-1765865704672 | D6: PH-01 | E6: Experience | F6: Purchase Management | G6: Coordinate purchasing from vendors based on demand, inventory gaps, and contract terms to ensure supply decisions align with pricing, compliance, and margin goals. | I6: Medium | J6: 8 | K6: 100 | L6: 3 | M6: 9
A7: DEL-006 | B7: CAP-006 | C7: BP-1765865704672 | D7: PH-01 | E7: Workflow | F7: Sales Order Processing | G7: Create, validate, price, and route sales orders through approvals to a “ready for fulfillment” state with full auditability. | I7: High | J7: 13 | K7: 140 | L7: 1 | M7: 5
A8: DEL-007 | B8: CAP-007 | C8: BP-1765865704672 | D8: PH-01 | E8: Workflow | F8: Fulfillment Execution | G8: Route fulfillment, allocate inventory, generate pick/pack/ship instructions, and confirm shipment with auditability. | I8: High | J8: 13 | K8: 100 | L8: 1 | M8: 5
A9: DEL-008 | B9: CAP-008 | C9: BP-1765865704672 | D9: PH-01 | E9: Workflow | F9: Purchase Replenishment | G9: Identify supply gaps, source eligible vendors, create POs with contract terms, receive goods, and close POs. | I9: Medium | J9: 8 | K9: 60 | L9: 1 | M9: 3
A10: DEL-009 | B10: FOUNDATIONS | C10: BP-1765865704672 | D10: PH-01 | E10: Foundation | F10: Foundations | G10: Infrastructure and foundational systems | K10: 160 | L10: 6 | M10: 18
A11: DEL-010 | B11: FUNC-031 | C11: BP-1765865704672 | D11: PH-01 | E11: Integration | F11: Inventory / WMS Service | G11: Source of truth for on-hand/available inventory and the execution surface for reservations and receiving updates. | I11: High | J11: 8 | K11: 40 | L11: 1 | M11: 1
A12: DEL-011 | B12: FUNC-032 | C12: BP-1765865704672 | D12: PH-01 | E12: Integration | F12: Vendor Portal / Supplier API | G12: External vendor system(s) providing item availability, lead times, SLAs, and certification status for sourcing and substitution decisions. | I12: High | J12: 8 | K12: 60 | L12: 1 | M12: 1
A13: DEL-012 | B13: FUNC-033 | C13: BP-1765865704672 | D13: PH-01 | E13: Integration | F13: Compliance Rules & Restrictions Service | G13: External or internal service that returns compliance rules, geo restrictions, and item-level regulatory attributes for evaluation at order and substitution time. | I13: High | J13: 8 | K13: 60 | L13: 1 | M13: 1
A14: DEL-013 | B14: FUNC-034 | C14: BP-1765865704672 | D14: PH-01 | E14: Integration | F14: Messaging / Event Bus | G14: Central eventing platform used to publish OMS domain events for consumers (ERP integration workers, dashboards, notifications). | I14: Medium | J14: 5 | K14: 40 | L14: 1 | M14: 1

Sheet EPIC - Epics
A1: Epic ID | B1: Strategy Ref | C1: Blueprint Ref | D1: Phase Ref ID | E1: Deliverable ID | F1: Deliverable Name | G1: Epic Type | H1: Epic Name | I1: Epic User Story | J1: Notes | K1: Complexity | L1: Effort | M1: Hours | N1: ELI Roll-Up
A2: EPIC-001 | B2: CAP-006 | C2: BP-1765865704672 | D2: PH-01 | E2: DEL-006 | F2: Sales Order Processing | G2: Workflow | H2: Sales Order Processing | I2: Create, validate, price, and route sales orders through approvals to a “ready for fulfillment” state with full auditability. | K2: High | L2: 13 | N2: 5
A3: EPIC-002 | B3: CAP-007 | C3: BP-1765865704672 | D3: PH-01 | E3: DEL-007 | F3: Fulfillment Execution | G3: Workflow | H3: Fulfillment Execution | I3: Route fulfillment, allocate inventory, generate pick/pack/ship instructions, and confirm shipment with auditability. | K3: High | L3: 13 | N3: 5
A4: EPIC-003 | B4: CAP-008 | C4: BP-1765865704672 | D4: PH-01 | E4: DEL-008 | F4: Purchase Replenishment | G4: Workflow | H4: Purchase Replenishment | I4: Identify supply gaps, source eligible vendors, create POs with contract terms, receive goods, and close POs. | K4: Medium | L4: 8 | N4: 3
A5: EPIC-004 | B5: CAP-014 | C5: BP-1765865704672 | D5: PH-01 | E5: DEL-009 | F5: Foundations | G5: Foundation | H5: Navigation and Component Library | I5: Establish the visual framework and reusable building blocks that define the application's user experience across OMS screens. | K5: Medium | L5: 8 | N5: 3
A6: EPIC-005 | B6: CAP-015 | C6: BP-1765865704672 | D6: PH-01 | E6: DEL-009 | F6: Foundations | G6: Foundation | H6: User Management | I6: Set up systems to onboard, store, and manage user accounts so each OMS user has an identity tied to permissions and settings. | K6: Medium | L6: 8 | N6: 3
A7: EPIC-006 | B7: CAP-016 | C7: BP-1765865704672 | D7: PH-01 | E7: DEL-009 | F7: Foundations | G7: Foundation | H7: Authentication & Security | I7: Protect OMS access with secure login flows, API protection, and encryption for sensitive contract, pricing, and compliance data. | K7: High | L7: 13 | N7: 3
A8: EPIC-007 | B8: CAP-017 | C8: BP-1765865704672 | D8: PH-01 | E8: DEL-009 | F8: Foundations | G8: Foundation | H8: Data Management | I8: Establish OMS core data models and APIs to support customers, contracts, orders, inventory reservations, fulfillment events, and purchasing. | K8: High | L8: 13 | N8: 3
A9: EPIC-008 | B9: CAP-018 | C9: BP-1765865704672 | D9: PH-01 | E9: DEL-009 | F9: Foundations | G9: Foundation | H9: Backend Infrastructure | I9: Provide core runtime, APIs, messaging, observability, and operational safeguards required to run OMS reliably across workflows and integrations. | K9: High | L9: 13 | N9: 3
A10: EPIC-009 | B10: CAP-019 | C10: BP-1765865704672 | D10: PH-01 | E10: DEL-009 | F10: Foundations | G10: Foundation | H10: DevOps | I10: Enable smooth development, deployment, and maintenance workflows across environments (local, staging, production) for OMS. | K10: Medium | L10: 8 | N10: 3
A11: EPIC-010 | B11: FUNC-001 | C11: BP-1765865704672 | D11: PH-01 | E11: DEL-001 | F11: Customer Management | G11: Use Case | H11: Manage Customers | I11: Create, update, and search customer profiles used for order association and downstream enforcement. | K11: Medium | L11: 5 | N11: 3
A12: EPIC-011 | B12: FUNC-002 | C12: BP-1765865704672 | D12: PH-01 | E12: DEL-001 | F12: Customer Management | G12: Use Case | H12: Associate Contracts to Customers | I12: Link active contracts to customers so pricing, terms, and decisioning are enforced at order time. | K12: High | L12: 8 | N12: 3
A13: EPIC-012 | B13: FUNC-003 | C13: BP-1765865704672 | D13: PH-01 | E13: DEL-001 | F13: Customer Management | G13: Use Case | H13: Manage Customer Compliance Requirements | I13: Define and apply customer-specific compliance constraints and maintain an auditable trail of compliance decisions. | K13: High | L13: 8 | N13: 3
... A30: EPIC-029 | B30: FUNC-034 | C30: BP-1765865704672 | D30: PH-01 | E30: DEL-013 | F30: Messaging / Event Bus | G30: System | H30: Messaging / Event Bus | I30: Central eventing platform used to publish OMS domain events for consumers (ERP integration workers, dashboards, notifications). | K30: Medium | L30: 5 | N30: 1

Sheet UG - User Groups
A1: User Group ID | B1: Name | C1: Description | D1: Objectives | E1: Challenges | F1: Benefits | G1: High Level User Story
A2: UG-01 | B2: Sales / Account Management | C2: Owns customer relationships and initiates sales orders, ensuring accurate customer context, pricing visibility, and contract alignment at order time. | D2: Create and submit accurate sales orders quickly; Ensure contract pricing is applied correctly on first pass; Respond confidently to customer questions and changes | E2: Contract logic historically scattered across spreadsheets and emails; Risk of quoting incorrect pricing or terms; Dependence on Ops or Finance for validations | F2: Faster order entry with fewer escalations; Higher order accuracy and customer trust; Clear visibility into pricing and approvals | G2: As a/An Sales / Account Management, I want Create and submit accurate sales orders quickly so that Faster order entry with fewer escalations.
A3: UG-02 | B3: Operations / Order Management | C3: Orchestrates order execution and exception handling, translating complex business rules into consistent fulfillment outcomes. | D3: Execute complex orders with system-driven decisions; Reduce manual intervention and operational firefighting; Ensure routing, sourcing, and substitutions follow rules and SLAs | E3: Reliance on tribal knowledge for fulfillment decisions; Multi-source fulfillment complexity; Frequent exceptions requiring rework | F3: Repeatable and predictable order execution; Fewer escalations and handoffs; Clear audit trail for operational decisions | G3: As a/An Operations / Order Management, I want Execute complex orders with system-driven decisions so that Repeatable and predictable order execution.
A4: UG-03 | B4: Warehouse & Fulfillment | C4: Executes picking, packing, shipping, and receiving activities across warehouses using system-generated instructions. | D4: Fulfill orders accurately and efficiently; Maintain inventory accuracy through timely updates; Execute substitutions and splits correctly | E4: Limited visibility into upstream decision context; Increased error risk from multi-warehouse splits; Inventory discrepancies due to delayed updates | F4: Clear pick/pack/ship instructions; Reduced fulfillment errors and rework; Faster throughput and inventory accuracy | G4: As a/An Warehouse & Fulfillment, I want Fulfill orders accurately and efficiently so that Clear pick/pack/ship instructions.
A5: UG-04 | B5: Finance / Compliance / Admin | C5: Governs pricing, approvals, compliance, and auditability to protect margins, ensure regulatory adherence, and maintain system integrity. | D5: Enforce contract pricing, approvals, and overrides; Maintain audit-ready records for pricing and compliance; Govern changes to contracts, rules, and vendors safely | E5: Margin erosion detected too late in the process; Manual audit preparation using spreadsheets; Risk when critical logic lives outside core systems | F5: Predictable margin protection; Clear, defensible audit trails; Centralized governance of rules and decisions | G5: As a/An Finance / Compliance / Admin, I want Enforce contract pricing, approvals, and overrides so that Predictable margin protection.

Sheet User Stories
A1: ELI ID | B1: deliverable | C1: epic | D1: Description | E1: as the | F1: I want to | G1: so i can | H1: Phase | I1: Tech Notes | J1: complexity | K1: hours | L1: sa | M1: qa | N1: total
A2: ELI-001 | B2: {=INDEX('ELI Data File'!I:I, MATCH(A2, 'ELI Data File'!A:A, 0))} -> Customer Management | C2: {=INDEX('ELI Data File'!J:J, MATCH(A2, 'ELI Data File'!A:A, 0))} -> Manage Customers | D2: {=INDEX('ELI Data File'!M:M, MATCH(A2, 'ELI Data File'!A:A, 0))} -> As a Sales user, I want to create a customer profile so that orders can be associated with the correct legal and billing entity. | E2: {=INDEX('ELI Data File'!H:H, MATCH(A2, 'ELI Data File'!A:A, 0))} -> Sales / Account Management | F2: =IFERROR(__xludf.DUMMYFUNCTION("AI(""Extract the Goal from the description""&D2)"),"create a customer profile") -> create a customer profile | G2: =IFERROR(__xludf.DUMMYFUNCTION("AI(""Extract the Value from the description""&D2)"),"orders can be associated with the correct legal and billing entity.") -> orders can be associated with the correct legal and billing entity. | H2: {=INDEX('ELI Data File'!D:D, MATCH(A2, 'ELI Data File'!A:A, 0))} -> PH-01 | J2: {=INDEX('ELI Data File'!O:O, MATCH(A2, 'ELI Data File'!A:A, 0))} -> Medium | K2: {=INDEX('ELI Data File'!P:P, MATCH(A2, 'ELI Data File'!A:A, 0))*4} -> 12 | L2: =ROUNDUP(K2*0.2,0) -> 3 | M2: 1 | N2: =SUM(K2:M2) -> 16
A3: ELI-002 | B3: {=INDEX('ELI Data File'!I:I, MATCH(A3, 'ELI Data File'!A:A, 0))} -> Customer Management | C3: {=INDEX('ELI Data File'!J:J, MATCH(A3, 'ELI Data File'!A:A, 0))} -> Manage Customers | D3: {=INDEX('ELI Data File'!M:M, MATCH(A3, 'ELI Data File'!A:A, 0))} -> As a Sales user, I want to update customer details so changes are reflected in future orders. | E3: {=INDEX('ELI Data File'!H:H, MATCH(A3, 'ELI Data File'!A:A, 0))} -> Sales / Account Management | F3: =IFERROR(__xludf.DUMMYFUNCTION("AI(""Extract the Goal from the description""&D3)"),"update customer details") -> update customer details | G3: =IFERROR(__xludf.DUMMYFUNCTION("AI(""Extract the Value from the description""&D3)"),"changes are reflected in future orders") -> changes are reflected in future orders | H3: {=INDEX('ELI Data File'!D:D, MATCH(A3, 'ELI Data File'!A:A, 0))} -> PH-01 | J3: {=INDEX('ELI Data File'!O:O, MATCH(A3, 'ELI Data File'!A:A, 0))} -> Medium | K3: {=INDEX('ELI Data File'!P:P, MATCH(A3, 'ELI Data File'!A:A, 0))*4} -> 12 | L3: =ROUNDUP(K3*0.2,0) -> 3 | M3: =ROUNDDOWN(SUM(K3:L3)/3,0) -> 5 | N3: =SUM(K3:M3) -> 20
A4: ELI-003 | B4: {=INDEX('ELI Data File'!I:I, MATCH(A4, 'ELI Data File'!A:A, 0))} -> Customer Management | C4: {=INDEX('ELI Data File'!J:J, MATCH(A4, 'ELI Data File'!A:A, 0))} -> Manage Customers | D4: {=INDEX('ELI Data File'!M:M, MATCH(A4, 'ELI Data File'!A:A, 0))} -> As an Ops user, I want to search customers quickly so I can validate order context without manual lookup. | E4: {=INDEX('ELI Data File'!H:H, MATCH(A4, 'ELI Data File'!A:A, 0))} -> Operations / Order Management | F4: =IFERROR(__xludf.DUMMYFUNCTION("AI(""Extract the Goal from the description""&D4)"),"search customers quickly") -> search customers quickly | G4: =IFERROR(__xludf.DUMMYFUNCTION("AI(""Extract the Value from the description""&D4)"),"validate order context without manual lookup.") -> validate order context without manual lookup. | H4: {=INDEX('ELI Data File'!D:D, MATCH(A4, 'ELI Data File'!A:A, 0))} -> PH-01 | J4: {=INDEX('ELI Data File'!O:O, MATCH(A4, 'ELI Data File'!A:A, 0))} -> Medium | K4: {=INDEX('ELI Data File'!P:P, MATCH(A4, 'ELI Data File'!A:A, 0))*4} -> 12 | L4: =ROUNDUP(K4*0.2,0) -> 3 | M4: =ROUNDDOWN(SUM(K4:L4)/3,0) -> 5 | N4: =SUM(K4:M4) -> 20
A5: ELI-004 | B5: {=INDEX('ELI Data File'!I:I, MATCH(A5, 'ELI Data File'!A:A, 0))} -> Customer Management | C5: {=INDEX('ELI Data File'!J:J, MATCH(A5, 'ELI Data File'!A:A, 0))} -> Associate Contracts to Customers | D5: {=INDEX('ELI Data File'!M:M, MATCH(A5, 'ELI Data File'!A:A, 0))} -> As an Admin, I want to associate an active contract to a customer so pricing and terms are enforced at order time. | E5: {=INDEX('ELI Data File'!H:H, MATCH(A5, 'ELI Data File'!A:A, 0))} -> Finance / Compliance / Admin | F5: =IFERROR(__xludf.DUMMYFUNCTION("AI(""Extract the Goal from the description""&D5)"),"associate an active contract to a customer") -> associate an active contract to a customer | G5: =IFERROR(__xludf.DUMMYFUNCTION("AI(""Extract the Value from the description""&D5)"),"pricing and terms are enforced at order time.") -> pricing and terms are enforced at order time. | H5: {=INDEX('ELI Data File'!D:D, MATCH(A5, 'ELI Data File'!A:A, 0))} -> PH-01 | J5: {=INDEX('ELI Data File'!O:O, MATCH(A5, 'ELI Data File'!A:A, 0))} -> Medium | K5: {=INDEX('ELI Data File'!P:P, MATCH(A5, 'ELI Data File'!A:A, 0))*4} -> 12 | L5: =ROUNDUP(K5*0.2,0) -> 3 | M5: =ROUNDDOWN(SUM(K5:L5)/3,0) -> 5 | N5: =SUM(K5:M5) -> 20
A6: ELI-005 | B6: {=INDEX('ELI Data File'!I:I, MATCH(A6, 'ELI Data File'!A:A, 0))} -> Customer Management | C6: {=INDEX('ELI Data File'!J:J, MATCH(A6, 'ELI Data File'!A:A, 0))} -> Associate Contracts to Customers | D6: {=INDEX('ELI Data File'!M:M, MATCH(A6, 'ELI Data File'!A:A, 0))} -> As Finance, I want to prevent orders for customers without active contracts to avoid uncontrolled pricing. | E6: {=INDEX('ELI Data File'!H:H, MATCH(A6, 'ELI Data File'!A:A, 0))} -> Finance / Compliance / Admin | F6: =IFERROR(__xludf.DUMMYFUNCTION("AI(""Extract the Goal from the description""&D6)"),"prevent orders for customers without active contracts") -> prevent orders for customers without active contracts | G6: =IFERROR(__xludf.DUMMYFUNCTION("AI(""Extract the Value from the description""&D6)"),"avoid uncontrolled pricing") -> avoid uncontrolled pricing | H6: {=INDEX('ELI Data File'!D:D, MATCH(A6, 'ELI Data File'!A:A, 0))} -> PH-01 | J6: {=INDEX('ELI Data File'!O:O, MATCH(A6, 'ELI Data File'!A:A, 0))} -> Medium | K6: {=INDEX('ELI Data File'!P:P, MATCH(A6, 'ELI Data File'!A:A, 0))*4} -> 12 | L6: =ROUNDUP(K6*0.2,0) -> 3 | M6: =ROUNDDOWN(SUM(K6:L6)/3,0) -> 5 | N6: =SUM(K6:M6) -> 20
A7: ELI-006 | B7: {=INDEX('ELI Data File'!I:I, MATCH(A7, 'ELI Data File'!A:A, 0))} -> Customer Management | C7: {=INDEX('ELI Data File'!J:J, MATCH(A7, 'ELI Data File'!A:A, 0))} -> Associate Contracts to Customers | D7: {=INDEX('ELI Data File'!M:M, MATCH(A7, 'ELI Data File'!A:A, 0))} -> As Finance, I want to view contract assignment history so audits do not rely on spreadsheets. | E7: {=INDEX('ELI Data File'!H:H, MATCH(A7, 'ELI Data File'!A:A, 0))} -> Finance / Compliance / Admin | F7: =IFERROR(__xludf.DUMMYFUNCTION("AI(""Extract the Goal from the description""&D7)"),"view contract assignment history") -> view contract assignment history | G7: =IFERROR(__xludf.DUMMYFUNCTION("AI(""Extract the Value from the description""&D7)"),"audits do not rely on spreadsheets.") -> audits do not rely on spreadsheets. | H7: {=INDEX('ELI Data File'!D:D, MATCH(A7, 'ELI Data File'!A:A, 0))} -> PH-01 | J7: {=INDEX('ELI Data File'!O:O, MATCH(A7, 'ELI Data File'!A:A, 0))} -> Medium | K7: {=INDEX('ELI Data File'!P:P, MATCH(A7, 'ELI Data File'!A:A, 0))*4} -> 12 | L7: =ROUNDUP(K7*0.2,0) -> 3 | M7: =ROUNDDOWN(SUM(K7:L7)/3,0) -> 5 | N7: =SUM(K7:M7) -> 20
A8: ELI-007 | B8: {=INDEX('ELI Data File'!I:I, MATCH(A8, 'ELI Data File'!A:A, 0))} -> Customer Management | C8: {=INDEX('ELI Data File'!J:J, MATCH(A8, 'ELI Data File'!A:A, 0))} -> Manage Customer Compliance Requirements | D8: {=INDEX('ELI Data File'!M:M, MATCH(A8, 'ELI Data File'!A:A, 0))} -> As a Compliance admin, I want to define customer-specific compliance rules so non-compliant orders are blocked. | E8: {=INDEX('ELI Data File'!H:H, MATCH(A8, 'ELI Data File'!A:A, 0))} -> Finance / Compliance / Admin | F8: =IFERROR(__xludf.DUMMYFUNCTION("AI(""Extract the Goal from the description""&D8)"),"define customer-specific compliance rules") -> define customer-specific compliance rules | G8: =IFERROR(__xludf.DUMMYFUNCTION("AI(""Extract the Value from the description""&D8)"),"non-compliant orders are blocked.") -> non-compliant orders are blocked. | H8: {=INDEX('ELI Data File'!D:D, MATCH(A8, 'ELI Data File'!A:A, 0))} -> PH-01 | J8: {=INDEX('ELI Data File'!O:O, MATCH(A8, 'ELI Data File'!A:A, 0))} -> Medium | K8: {=INDEX('ELI Data File'!P:P, MATCH(A8, 'ELI Data File'!A:A, 0))*4} -> 12 | L8: =ROUNDUP(K8*0.2,0) -> 3 | M8: =ROUNDDOWN(SUM(K8:L8)/3,0) -> 5 | N8: =SUM(K8:M8) -> 20
A9: ELI-008 | B9: {=INDEX('ELI Data File'!I:I, MATCH(A9, 'ELI Data File'!A:A, 0))} -> Customer Management | C9: {=INDEX('ELI Data File'!J:J, MATCH(A9, 'ELI Data File'!A:A, 0))} -> Manage Customer Compliance Requirements | D9: {=INDEX('ELI Data File'!M:M, MATCH(A9, 'ELI Data File'!A:A, 0))} -> As Ops, I want compliance rules evaluated automatically so I don’t interpret regulations manually. | E9: {=INDEX('ELI Data File'!H:H, MATCH(A9, 'ELI Data File'!A:A, 0))} -> Operations / Order Management | F9: =IFERROR(__xludf.DUMMYFUNCTION("AI(""Extract the Goal from the description""&D9)"),"compliance rules evaluated automatically") -> compliance rules evaluated automatically | G9: =IFERROR(__xludf.DUMMYFUNCTION("AI(""Extract the Value from the description""&D9)"),"I don’t interpret regulations manually.") -> I don’t interpret regulations manually. | H9: {=INDEX('ELI Data File'!D:D, MATCH(A9, 'ELI Data File'!A:A, 0))} -> PH-01 | J9: {=INDEX('ELI Data File'!O:O, MATCH(A9, 'ELI Data File'!A:A, 0))} -> Medium | K9: {=INDEX('ELI Data File'!P:P, MATCH(A9, 'ELI Data File'!A:A, 0))*4} -> 12 | L9: =ROUNDUP(K9*0.2,0) -> 3 | M9: =ROUNDDOWN(SUM(K9:L9)/3,0) -> 5 | N9: =SUM(K9:M9) -> 20
A10: ELI-009 | B10: {=INDEX('ELI Data File'!I:I, MATCH(A10, 'ELI Data File'!A:A, 0))} -> Customer Management | C10: {=INDEX('ELI Data File'!J:J, MATCH(A10, 'ELI Data File'!A:A, 0))} -> Manage Customer Compliance Requirements | D10: {=INDEX('ELI Data File'!M:M, MATCH(A10, 'ELI Data File'!A:A, 0))} -> As Compliance, I want an audit trail of compliance decisions so regulatory reviews are defensible. | E10: {=INDEX('ELI Data File'!H:H, MATCH(A10, 'ELI Data File'!A:A, 0))} -> Finance / Compliance / Admin | F10: =IFERROR(__xludf.DUMMYFUNCTION("AI(""Extract the Goal from the description""&D10)"),"want an audit trail of compliance decisions") -> want an audit trail of compliance decisions | G10: =IFERROR(__xludf.DUMMYFUNCTION("AI(""Extract the Value from the description""&D10)"),"regulatory reviews are defensible") -> regulatory reviews are defensible | H10: {=INDEX('ELI Data File'!D:D, MATCH(A10, 'ELI Data File'!A:A, 0))} -> PH-01 | J10: {=INDEX('ELI Data File'!O:O, MATCH(A10, 'ELI Data File'!A:A, 0))} -> Medium | K10: {=INDEX('ELI Data File'!P:P, MATCH(A10, 'ELI Data File'!A:A, 0))*4} -> 12 | L10: =ROUNDUP(K10*0.2,0) -> 3 | M10: =ROUNDDOWN(SUM(K10:L10)/3,0) -> 5 | N10: =SUM(K10:M10) -> 20
A11: ELI-010 | B11: {=INDEX('ELI Data File'!I:I, MATCH(A11, 'ELI Data File'!A:A, 0))} -> Inventory Management | C11: {=INDEX('ELI Data File'!J:J, MATCH(A11, 'ELI Data File'!A:A, 0))} -> Manage Inventory | D11: {=INDEX('ELI Data File'!M:M, MATCH(A11, 'ELI Data File'!A:A, 0))} -> As an Ops user, I want to view real-time inventory levels so I can make accurate fulfillment decisions. | E11: {=INDEX('ELI Data File'!H:H, MATCH(A11, 'ELI Data File'!A:A, 0))} -> Operations / Order Management | F11: =IFERROR(__xludf.DUMMYFUNCTION("AI(""Extract the Goal from the description""&D11)"),"view real-time inventory levels") -> view real-time inventory levels | G11: =IFERROR(__xludf.DUMMYFUNCTION("AI(""Extract the Value from the description""&D11)"),"so I can make accurate fulfillment decisions.") -> so I can make accurate fulfillment decisions. | H11: {=INDEX('ELI Data File'!D:D, MATCH(A11, 'ELI Data File'!A:A, 0))} -> PH-01 | J11: {=INDEX('ELI Data File'!O:O, MATCH(A11, 'ELI Data File'!A:A, 0))} -> Medium | K11: {=INDEX('ELI Data File'!P:P, MATCH(A11, 'ELI Data File'!A:A, 0))*4} -> 12 | L11: =ROUNDUP(K11*0.2,0) -> 3 | M11: =ROUNDDOWN(SUM(K11:L11)/3,0) -> 5 | N11: =SUM(K11:M11) -> 20
A12: ELI-011 | B12: {=INDEX('ELI Data File'!I:I, MATCH(A12, 'ELI Data File'!A:A, 0))} -> Inventory Management | C12: {=INDEX('ELI Data File'!J:J, MATCH(A12, 'ELI Data File'!A:A, 0))} -> Manage Inventory | D12: {=INDEX('ELI Data File'!M:M, MATCH(A12, 'ELI Data File'!A:A, 0))} -> As a Warehouse user, I want to adjust inventory quantities so physical discrepancies are reflected in the system. | E12: {=INDEX('ELI Data File'!H:H, MATCH(A12, 'ELI Data File'!A:A, 0))} -> Warehouse & Fulfillment | F12: =IFERROR(__xludf.DUMMYFUNCTION("AI(""Extract the Goal from the description""&D12)"),"adjust inventory quantities") -> adjust inventory quantities | G12: =IFERROR(__xludf.DUMMYFUNCTION("AI(""Extract the Value from the description""&D12)"),"physical discrepancies are reflected in the system.") -> physical discrepancies are reflected in the system. | H12: {=INDEX('ELI Data File'!D:D, MATCH(A12, 'ELI Data File'!A:A, 0))} -> PH-01 | J12: {=INDEX('ELI Data File'!O:O, MATCH(A12, 'ELI Data File'!A:A, 0))} -> Medium | K12: {=INDEX('ELI Data File'!P:P, MATCH(A12, 'ELI Data File'!A:A, 0))*4} -> 12 | L12: =ROUNDUP(K12*0.2,0) -> 3 | M12: =ROUNDDOWN(SUM(K12:L12)/3,0) -> 5 | N12: =SUM(K12:M12) -> 20
A13: ELI-012 | B13: {=INDEX('ELI Data File'!I:I, MATCH(A13, 'ELI Data File'!A:A, 0))} -> Inventory Management | C13: {=INDEX('ELI Data File'!J:J, MATCH(A13, 'ELI Data File'!A:A, 0))} -> Manage Inventory | D13: {=INDEX('ELI Data File'!M:M, MATCH(A13, 'ELI Data File'!A:A, 0))} -> As a Warehouse user, I want to receive inventory so newly arrived stock becomes available for allocation. | E13: {=INDEX('ELI Data File'!H:H, MATCH(A13, 'ELI Data File'!A:A, 0))} -> Warehouse & Fulfillment | F13: =IFERROR(__xludf.DUMMYFUNCTION("AI(""Extract the Goal from the description""&D13)"),"receive inventory") -> receive inventory | G13: =IFERROR(__xludf.DUMMYFUNCTION("AI(""Extract the Value from the description""&D13)"),"newly arrived stock becomes available for allocation.") -> newly arrived stock becomes available for allocation. | H13: {=INDEX('ELI Data File'!D:D, MATCH(A13, 'ELI Data File'!A:A, 0))} -> PH-01 | J13: {=INDEX('ELI Data File'!O:O, MATCH(A13, 'ELI Data File'!A:A, 0))} -> Medium | K13: {=INDEX('ELI Data File'!P:P, MATCH(A13, 'ELI Data File'!A:A, 0))*4} -> 12 | L13: =ROUNDUP(K13*0.2,0) -> 3 | M13: =ROUNDDOWN(SUM(K13:L13)/3,0) -> 5 | N13: =SUM(K13:M13) -> 20
A14: ELI-013 | B14: {=INDEX('ELI Data File'!I:I, MATCH(A14, 'ELI Data File'!A:A, 0))} -> Inventory Management | C14: {=INDEX('ELI Data File'!J:J, MATCH(A14, 'ELI Data File'!A:A, 0))} -> Track Inventory Availability Across Sources | D14: {=INDEX('ELI Data File'!M:M, MATCH(A14, 'ELI Data File'!A:A, 0))} -> As Ops, I want to see inventory across all warehouses so I can plan multi-location fulfillment. | E14: {=INDEX('ELI Data File'!H:H, MATCH(A14, 'ELI Data File'!A:A, 0))} -> Operations / Order Management | F14: =IFERROR(__xludf.DUMMYFUNCTION("AI(""Extract the Goal from the description""&D14)"),"see inventory across all warehouses") -> see inventory across all warehouses | G14: =IFERROR(__xludf.DUMMYFUNCTION("AI(""Extract the Value from the description""&D14)"),"plan multi-location fulfillment.") -> plan multi-location fulfillment. | H14: {=INDEX('ELI Data File'!D:D, MATCH(A14, 'ELI Data File'!A:A, 0))} -> PH-01 | J14: {=INDEX('ELI Data File'!O:O, MATCH(A14, 'ELI Data File'!A:A, 0))} -> Medium | K14: {=INDEX('ELI Data File'!P:P, MATCH(A14, 'ELI Data File'!A:A, 0))*4} -> 12 | L14: =ROUNDUP(K14*0.2,0) -> 3 | M14: =ROUNDDOWN(SUM(K14:L14)/3,0) -> 5 | N14: =SUM(K14:M14) -> 20
A15: ELI-014 | B15: {=INDEX('ELI Data File'!I:I, MATCH(A15, 'ELI Data File'!A:A, 0))} -> Inventory Management | C15: {=INDEX('ELI Data File'!J:J, MATCH(A15, 'ELI Data File'!A:A, 0))} -> Track Inventory Availability Across Sources | D15: {=INDEX('ELI Data File'!M:M, MATCH(A15, 'ELI Data File'!A:A, 0))} -> As Ops, I want vendor-supplied availability included so out-of-stock items can still be sourced compliantly. | E15: {=INDEX('ELI Data File'!H:H, MATCH(A15, 'ELI Data File'!A:A, 0))} -> Operations / Order Management | F15: =IFERROR(__xludf.DUMMYFUNCTION("AI(""Extract the Goal from the description""&D15)"),"include vendor-supplied availability") -> include vendor-supplied availability | G15: =IFERROR(__xludf.DUMMYFUNCTION("AI(""Extract the Value from the description""&D15)"),"so out-of-stock items can still be sourced compliantly.") -> so out-of-stock items can still be sourced compliantly. | H15: {=INDEX('ELI Data File'!D:D, MATCH(A15, 'ELI Data File'!A:A, 0))} -> PH-01 | J15: {=INDEX('ELI Data File'!O:O, MATCH(A15, 'ELI Data File'!A:A, 0))} -> Medium | K15: {=INDEX('ELI Data File'!P:P, MATCH(A15, 'ELI Data File'!A:A, 0))*4} -> 12 | L15: =ROUNDUP(K15*0.2,0) -> 3 | M15: =ROUNDDOWN(SUM(K15:L15)/3,0) -> 5 | N15: =SUM(K15:M15) -> 20
A16: ELI-015 | B16: {=INDEX('ELI Data File'!I:I, MATCH(A16, 'ELI Data File'!A:A, 0))} -> Inventory Management | C16: {=INDEX('ELI Data File'!J:J, MATCH(A16, 'ELI Data File'!A:A, 0))} -> Track Inventory Availability Across Sources | D16: {=INDEX('ELI Data File'!M:M, MATCH(A16, 'ELI Data File'!A:A, 0))} -> As Finance, I want to distinguish allocatable inventory from informational stock so financial exposure is controlled. | E16: {=INDEX('ELI Data File'!H:H, MATCH(A16, 'ELI Data File'!A:A, 0))} -> Finance / Compliance / Admin | F16: =IFERROR(__xludf.DUMMYFUNCTION("AI(""Extract the Goal from the description""&D16)"),"distinguish allocatable inventory from informational stock") -> distinguish allocatable inventory from informational stock | G16: =IFERROR(__xludf.DUMMYFUNCTION("AI(""Extract the Value from the description""&D16)"),"financial exposure is controlled.") -> financial exposure is controlled. | H16: {=INDEX('ELI Data File'!D:D, MATCH(A16, 'ELI Data File'!A:A, 0))} -> PH-01 | J16: {=INDEX('ELI Data File'!O:O, MATCH(A16, 'ELI Data File'!A:A, 0))} -> Medium | K16: {=INDEX('ELI Data File'!P:P, MATCH(A16, 'ELI Data File'!A:A, 0))*4} -> 12 | L16: =ROUNDUP(K16*0.2,0) -> 3 | M16: =ROUNDDOWN(SUM(K16:L16)/3,0) -> 5 | N16: =SUM(K16:M16) -> 20
A17: ELI-016 | B17: {=INDEX('ELI Data File'!I:I, MATCH(A17, 'ELI Data File'!A:A, 0))} -> Inventory Management | C17: {=INDEX('ELI Data File'!J:J, MATCH(A17, 'ELI Data File'!A:A, 0))} -> Allocate Inventory to Orders | D17: {=INDEX('ELI Data File'!M:M, MATCH(A17, 'ELI Data File'!A:A, 0))} -> As Ops, I want to reserve inventory so stock is protected for committed orders. | E17: {=INDEX('ELI Data File'!H:H, MATCH(A17, 'ELI Data File'!A:A, 0))} -> Operations / Order Management | F17: =IFERROR(__xludf.DUMMYFUNCTION("AI(""Extract the Goal from the description""&D17)"),"reserve inventory") -> reserve inventory | G17: =IFERROR(__xludf.DUMMYFUNCTION("AI(""Extract the Value from the description""&D17)"),"stock is protected for committed orders.") -> stock is protected for committed orders. | H17: {=INDEX('ELI Data File'!D:D, MATCH(A17, 'ELI Data File'!A:A, 0))} -> PH-01 | J17: {=INDEX('ELI Data File'!O:O, MATCH(A17, 'ELI Data File'!A:A, 0))} -> Medium | K17: {=INDEX('ELI Data File'!P:P, MATCH(A17, 'ELI Data File'!A:A, 0))*4} -> 12 | L17: =ROUNDUP(K17*0.2,0) -> 3 | M17: =ROUNDDOWN(SUM(K17:L17)/3,0) -> 5 | N17: =SUM(K17:M17) -> 20
A18: ELI-017 | B18: {=INDEX('ELI Data File'!I:I, MATCH(A18, 'ELI Data File'!A:A, 0))} -> Inventory Management | C18: {=INDEX('ELI Data File'!J:J, MATCH(A18, 'ELI Data File'!A:A, 0))} -> Allocate Inventory to Orders | D18: {=INDEX('ELI Data File'!M:M, MATCH(A18, 'ELI Data File'!A:A, 0))} -> As Ops, I want reserved inventory released when an order is canceled so stock is reusable. | E18: {=INDEX('ELI Data File'!H:H, MATCH(A18, 'ELI Data File'!A:A, 0))} -> Operations / Order Management | F18: =IFERROR(__xludf.DUMMYFUNCTION("AI(""Extract the Goal from the description""&D18)"),"reserved inventory released when an order is canceled") -> reserved inventory released when an order is canceled | G18: =IFERROR(__xludf.DUMMYFUNCTION("AI(""Extract the Value from the description""&D18)"),"stock is reusable") -> stock is reusable | H18: {=INDEX('ELI Data File'!D:D, MATCH(A18, 'ELI Data File'!A:A, 0))} -> PH-01 | J18: {=INDEX('ELI Data File'!O:O, MATCH(A18, 'ELI Data File'!A:A, 0))} -> Medium | K18: {=INDEX('ELI Data File'!P:P, MATCH(A18, 'ELI Data File'!A:A, 0))*4} -> 12 | L18: =ROUNDUP(K18*0.2,0) -> 3 | M18: =ROUNDDOWN(SUM(K18:L18)/3,0) -> 5 | N18: =SUM(K18:M18) -> 20
A19: ELI-018 | B19: {=INDEX('ELI Data File'!I:I, MATCH(A19, 'ELI Data File'!A:A, 0))} -> Inventory Management | C19: {=INDEX('ELI Data File'!J:J, MATCH(A19, 'ELI Data File'!A:A, 0))} -> Allocate Inventory to Orders | D19: {=INDEX('ELI Data File'!M:M, MATCH(A19, 'ELI Data File'!A:A, 0))} -> As Ops, I want inventory reallocated when orders change so fulfillment remains accurate. | E19: {=INDEX('ELI Data File'!H:H, MATCH(A19, 'ELI Data File'!A:A, 0))} -> Operations / Order Management | F19: =IFERROR(__xludf.DUMMYFUNCTION("AI(""Extract the Goal from the description""&D19)"),"I want inventory reallocated when orders change") -> I want inventory reallocated when orders change | G19: =IFERROR(__xludf.DUMMYFUNCTION("AI(""Extract the Value from the description""&D19)"),"fulfillment remains accurate") -> fulfillment remains accurate | H19: {=INDEX('ELI Data File'!D:D, MATCH(A19, 'ELI Data File'!A:A, 0))} -> PH-01 | J19: {=INDEX('ELI Data File'!O:O, MATCH(A19, 'ELI Data File'!A:A, 0))} -> Medium | K19: {=INDEX('ELI Data File'!P:P, MATCH(A19, 'ELI Data File'!A:A, 0))*4} -> 12 | L19: =ROUNDUP(K19*0.2,0) -> 3 | M19: =ROUNDDOWN(SUM(K19:L19)/3,0) -> 5 | N19: =SUM(K19:M19) -> 20
A20: ELI-019 | B20: {=INDEX('ELI Data File'!I:I, MATCH(A20, 'ELI Data File'!A:A, 0))} -> Order Management | C20: {=INDEX('ELI Data File'!J:J, MATCH(A20, 'ELI Data File'!A:A, 0))} -> Create Sales Order | D20: {=INDEX('ELI Data File'!M:M, MATCH(A20, 'ELI Data File'!A:A, 0))} -> As a Sales user, I want to create a sales order tied to a customer so contract pricing and rules are applied automatically. | E20: {=INDEX('ELI Data File'!H:H, MATCH(A20, 'ELI Data File'!A:A, 0))} -> Sales / Account Management | F20: =IFERROR(__xludf.DUMMYFUNCTION("AI(""Extract the Goal from the description""&D20)"),"create a sales order tied to a customer") -> create a sales order tied to a customer | G20: =IFERROR(__xludf.DUMMYFUNCTION("AI(""Extract the Value from the description""&D20)"),"contract pricing and rules are applied automatically.") -> contract pricing and rules are applied automatically. | H20: {=INDEX('ELI Data File'!D:D, MATCH(A20, 'ELI Data File'!A:A, 0))} -> PH-01 | J20: {=INDEX('ELI Data File'!O:O, MATCH(A20, 'ELI Data File'!A:A, 0))} -> Medium | K20: {=INDEX('ELI Data File'!P:P, MATCH(A20, 'ELI Data File'!A:A, 0))*4} -> 12 | L20: =ROUNDUP(K20*0.2,0) -> 3 | M20: =ROUNDDOWN(SUM(K20:L20)/3,0) -> 5 | N20: =SUM(K20:M20) -> 20
A21: ELI-020 | B21: {=INDEX('ELI Data File'!I:I, MATCH(A21, 'ELI Data File'!A:A, 0))} -> Order Management | C21: {=INDEX('ELI Data File'!J:J, MATCH(A21, 'ELI Data File'!A:A, 0))} -> Create Sales Order | D21: {=INDEX('ELI Data File'!M:M, MATCH(A21, 'ELI Data File'!A:A, 0))} -> As a Sales user, I want required order data validated so incomplete orders cannot proceed. | E21: {=INDEX('ELI Data File'!H:H, MATCH(A21, 'ELI Data File'!A:A, 0))} -> Sales / Account Management | F21: =IFERROR(__xludf.DUMMYFUNCTION("AI(""Extract the Goal from the description""&D21)"),"required order data validated") -> required order data validated | G21: =IFERROR(__xludf.DUMMYFUNCTION("AI(""Extract the Value from the description""&D21)"),"incomplete orders cannot proceed.") -> incomplete orders cannot proceed. | H21: {=INDEX('ELI Data File'!D:D, MATCH(A21, 'ELI Data File'!A:A, 0))} -> PH-01 | J21: {=INDEX('ELI Data File'!O:O, MATCH(A21, 'ELI Data File'!A:A, 0))} -> Medium | K21: {=INDEX('ELI Data File'!P:P, MATCH(A21, 'ELI Data File'!A:A, 0))*4} -> 12 | L21: =ROUNDUP(K21*0.2,0) -> 3 | M21: =ROUNDDOWN(SUM(K21:L21)/3,0) -> 5 | N21: =SUM(K21:M21) -> 20
A22: ELI-021 | B22: {=INDEX('ELI Data File'!I:I, MATCH(A22, 'ELI Data File'!A:A, 0))} -> Order Management | C22: {=INDEX('ELI Data File'!J:J, MATCH(A22, 'ELI Data File'!A:A, 0))} -> Create Sales Order | D22: {=INDEX('ELI Data File'!M:M, MATCH(A22, 'ELI Data File'!A:A, 0))} -> As a Sales user, I want to preview pricing so I can confirm totals before submitting the order. | E22: {=INDEX('ELI Data File'!H:H, MATCH(A22, 'ELI Data File'!A:A, 0))} -> Sales / Account Management | F22: =IFERROR(__xludf.DUMMYFUNCTION("AI(""Extract the Goal from the description""&D22)"),"preview pricing") -> preview pricing | G22: =IFERROR(__xludf.DUMMYFUNCTION("AI(""Extract the Value from the description""&D22)"),"confirm totals before submitting the order.") -> confirm totals before submitting the order. | H22: {=INDEX('ELI Data File'!D:D, MATCH(A22, 'ELI Data File'!A:A, 0))} -> PH-01 | J22: {=INDEX('ELI Data File'!O:O, MATCH(A22, 'ELI Data File'!A:A, 0))} -> Medium | K22: {=INDEX('ELI Data File'!P:P, MATCH(A22, 'ELI Data File'!A:A, 0))*4} -> 12 | L22: =ROUNDUP(K22*0.2,0) -> 3 | M22: =ROUNDDOWN(SUM(K22:L22)/3,0) -> 5 | N22: =SUM(K22:M22) -> 20
A23: ELI-022 | B23: {=INDEX('ELI Data File'!I:I, MATCH(A23, 'ELI Data File'!A:A, 0))} -> Order Management | C23: {=INDEX('ELI Data File'!J:J, MATCH(A23, 'ELI Data File'!A:A, 0))} -> Evaluate Contract Pricing & Terms | D23: {=INDEX('ELI Data File'!M:M, MATCH(A23, 'ELI Data File'!A:A, 0))} -> As Finance, I want tiered pricing applied automatically so pricing is consistent and auditable. | E23: {=INDEX('ELI Data File'!H:H, MATCH(A23, 'ELI Data File'!A:A, 0))} -> Finance / Compliance / Admin | F23: =IFERROR(__xludf.DUMMYFUNCTION("AI(""Extract the Goal from the description""&D23)"),"apply tiered pricing automatically") -> apply tiered pricing automatically | G23: =IFERROR(__xludf.DUMMYFUNCTION("AI(""Extract the Value from the description""&D23)"),"pricing is consistent and auditable.") -> pricing is consistent and auditable. | H23: {=INDEX('ELI Data File'!D:D, MATCH(A23, 'ELI Data File'!A:A, 0))} -> PH-01 | J23: {=INDEX('ELI Data File'!O:O, MATCH(A23, 'ELI Data File'!A:A, 0))} -> Medium | K23: {=INDEX('ELI Data File'!P:P, MATCH(A23, 'ELI Data File'!A:A, 0))*4} -> 12 | L23: =ROUNDUP(K23*0.2,0) -> 3 | M23: =ROUNDDOWN(SUM(K23:L23)/3,0) -> 5 | N23: =SUM(K23:M23) -> 20
A24: ELI-023 | B24: {=INDEX('ELI Data File'!I:I, MATCH(A24, 'ELI Data File'!A:A, 0))} -> Order Management | C24: {=INDEX('ELI Data File'!J:J, MATCH(A24, 'ELI Data File'!A:A, 0))} -> Evaluate Contract Pricing & Terms | D24: {=INDEX('ELI Data File'!M:M, MATCH(A24, 'ELI Data File'!A:A, 0))} -> As Finance, I want rebates and penalties enforced so margins and commitments are protected. | E24: {=INDEX('ELI Data File'!H:H, MATCH(A24, 'ELI Data File'!A:A, 0))} -> Finance / Compliance / Admin | F24: =IFERROR(__xludf.DUMMYFUNCTION("AI(""Extract the Goal from the description""&D24)"),"rebates and penalties enforced") -> rebates and penalties enforced | G24: =IFERROR(__xludf.DUMMYFUNCTION("AI(""Extract the Value from the description""&D24)"),"margins and commitments are protected.") -> margins and commitments are protected. | H24: {=INDEX('ELI Data File'!D:D, MATCH(A24, 'ELI Data File'!A:A, 0))} -> PH-01 | J24: {=INDEX('ELI Data File'!O:O, MATCH(A24, 'ELI Data File'!A:A, 0))} -> Medium | K24: {=INDEX('ELI Data File'!P:P, MATCH(A24, 'ELI Data File'!A:A, 0))*4} -> 12 | L24: =ROUNDUP(K24*0.2,0) -> 3 | M24: =ROUNDDOWN(SUM(K24:L24)/3,0) -> 5 | N24: =SUM(K24:M24) -> 20
A25: ELI-024 | B25: {=INDEX('ELI Data File'!I:I, MATCH(A25, 'ELI Data File'!A:A, 0))} -> Order Management | C25: {=INDEX('ELI Data File'!J:J, MATCH(A25, 'ELI Data File'!A:A, 0))} -> Evaluate Contract Pricing & Terms | D25: {=INDEX('ELI Data File'!M:M, MATCH(A25, 'ELI Data File'!A:A, 0))} -> As Ops, I want pricing recalculated when an order changes so pricing remains accurate. | E25: {=INDEX('ELI Data File'!H:H, MATCH(A25, 'ELI Data File'!A:A, 0))} -> Operations / Order Management | F25: =IFERROR(__xludf.DUMMYFUNCTION("AI(""Extract the Goal from the description""&D25)"),"recalculated when an order changes") -> recalculated when an order changes | G25: =IFERROR(__xludf.DUMMYFUNCTION("AI(""Extract the Value from the description""&D25)"),"pricing remains accurate.") -> pricing remains accurate. | H25: {=INDEX('ELI Data File'!D:D, MATCH(A25, 'ELI Data File'!A:A, 0))} -> PH-01 | J25: {=INDEX('ELI Data File'!O:O, MATCH(A25, 'ELI Data File'!A:A, 0))} -> Medium | K25: {=INDEX('ELI Data File'!P:P, MATCH(A25, 'ELI Data File'!A:A, 0))*4} -> 12 | L25: =ROUNDUP(K25*0.2,0) -> 3 | M25: =ROUNDDOWN(SUM(K25:L25)/3,0) -> 5 | N25: =SUM(K25:M25) -> 20
A26: ELI-025 | B26: {=INDEX('ELI Data File'!I:I, MATCH(A26, 'ELI Data File'!A:A, 0))} -> Order Management | C26: {=INDEX('ELI Data File'!J:J, MATCH(A26, 'ELI Data File'!A:A, 0))} -> Manage Sales Order Lifecycle | D26: {=INDEX('ELI Data File'!M:M, MATCH(A26, 'ELI Data File'!A:A, 0))} -> As Ops, I want to view order status so I can track progress without manual follow-up. | E26: {=INDEX('ELI Data File'!H:H, MATCH(A26, 'ELI Data File'!A:A, 0))} -> Operations / Order Management | F26: =IFERROR(__xludf.DUMMYFUNCTION("AI(""Extract the Goal from the description""&D26)"),"view order status") -> view order status | G26: =IFERROR(__xludf.DUMMYFUNCTION("AI(""Extract the Value from the description""&D26)"),"track progress without manual follow-up.") -> track progress without manual follow-up. | H26: {=INDEX('ELI Data File'!D:D, MATCH(A26, 'ELI Data File'!A:A, 0))} -> PH-01 | J26: {=INDEX('ELI Data File'!O:O, MATCH(A26, 'ELI Data File'!A:A, 0))} -> Medium | K26: {=INDEX('ELI Data File'!P:P, MATCH(A26, 'ELI Data File'!A:A, 0))*4} -> 12 | L26: =ROUNDUP(K26*0.2,0) -> 3 | M26: =ROUNDDOWN(SUM(K26:L26)/3,0) -> 5 | N26: =SUM(K26:M26) -> 20
A27: ELI-026 | B27: {=INDEX('ELI Data File'!I:I, MATCH(A27, 'ELI Data File'!A:A, 0))} -> Order Management | C27: {=INDEX('ELI Data File'!J:J, MATCH(A27, 'ELI Data File'!A:A, 0))} -> Manage Sales Order Lifecycle | D27: {=INDEX('ELI Data File'!M:M, MATCH(A27, 'ELI Data File'!A:A, 0))} -> As Ops, I want to update order status so downstream processes stay aligned. | E27: {=INDEX('ELI Data File'!H:H, MATCH(A27, 'ELI Data File'!A:A, 0))} -> Operations / Order Management | F27: =IFERROR(__xludf.DUMMYFUNCTION("AI(""Extract the Goal from the description""&D27)"),"update order status") -> update order status | G27: =IFERROR(__xludf.DUMMYFUNCTION("AI(""Extract the Value from the description""&D27)"),"downstream processes stay aligned") -> downstream processes stay aligned | H27: {=INDEX('ELI Data File'!D:D, MATCH(A27, 'ELI Data File'!A:A, 0))} -> PH-01 | J27: {=INDEX('ELI Data File'!O:O, MATCH(A27, 'ELI Data File'!A:A, 0))} -> Medium | K27: {=INDEX('ELI Data File'!P:P, MATCH(A27, 'ELI Data File'!A:A, 0))*4} -> 12 | L27: =ROUNDUP(K27*0.2,0) -> 3 | M27: =ROUNDDOWN(SUM(K27:L27)/3,0) -> 5 | N27: =SUM(K27:M27) -> 20
A28: ELI-027 | B28: {=INDEX('ELI Data File'!I:I, MATCH(A28, 'ELI Data File'!A:A, 0))} -> Order Management | C28: {=INDEX('ELI Data File'!J:J, MATCH(A28, 'ELI Data File'!A:A, 0))} -> Manage Sales Order Lifecycle | D28: {=INDEX('ELI Data File'!M:M, MATCH(A28, 'ELI Data File'!A:A, 0))} -> As Sales, I want to cancel an order so inventory and commitments are released correctly. | E28: {=INDEX('ELI Data File'!H:H, MATCH(A28, 'ELI Data File'!A:A, 0))} -> Sales / Account Management | F28: =IFERROR(__xludf.DUMMYFUNCTION("AI(""Extract the Goal from the description""&D28)"),"cancel an order") -> cancel an order | G28: =IFERROR(__xludf.DUMMYFUNCTION("AI(""Extract the Value from the description""&D28)"),"inventory and commitments are released correctly.") -> inventory and commitments are released correctly. | H28: {=INDEX('ELI Data File'!D:D, MATCH(A28, 'ELI Data File'!A:A, 0))} -> PH-01 | J28: {=INDEX('ELI Data File'!O:O, MATCH(A28, 'ELI Data File'!A:A, 0))} -> Medium | K28: {=INDEX('ELI Data File'!P:P, MATCH(A28, 'ELI Data File'!A:A, 0))*4} -> 12 | L28: =ROUNDUP(K28*0.2,0) -> 3 | M28: =ROUNDDOWN(SUM(K28:L28)/3,0) -> 5 | N28: =SUM(K28:M28) -> 20
A29: ELI-028 | B29: {=INDEX('ELI Data File'!I:I, MATCH(A29, 'ELI Data File'!A:A, 0))} -> Order Management | C29: {=INDEX('ELI Data File'!J:J, MATCH(A29, 'ELI Data File'!A:A, 0))} -> Approve Order Exceptions & Overrides | D29: {=INDEX('ELI Data File'!M:M, MATCH(A29, 'ELI Data File'!A:A, 0))} -> As Finance, I want orders that exceed thresholds routed for approval so risk is controlled. | E29: {=INDEX('ELI Data File'!H:H, MATCH(A29, 'ELI Data File'!A:A, 0))} -> Finance / Compliance / Admin | F29: =IFERROR(__xludf.DUMMYFUNCTION("AI(""Extract the Goal from the description""&D29)"),"orders that exceed thresholds routed for approval") -> orders that exceed thresholds routed for approval | G29: =IFERROR(__xludf.DUMMYFUNCTION("AI(""Extract the Value from the description""&D29)"),"risk is controlled") -> risk is controlled | H29: {=INDEX('ELI Data File'!D:D, MATCH(A29, 'ELI Data File'!A:A, 0))} -> PH-01 | J29: {=INDEX('ELI Data File'!O:O, MATCH(A29, 'ELI Data File'!A:A, 0))} -> Medium | K29: {=INDEX('ELI Data File'!P:P, MATCH(A29, 'ELI Data File'!A:A, 0))*4} -> 12 | L29: =ROUNDUP(K29*0.2,0) -> 3 | M29: =ROUNDDOWN(SUM(K29:L29)/3,0) -> 5 | N29: =SUM(K29:M29) -> 20
A30: ELI-029 | B30: {=INDEX('ELI Data File'!I:I, MATCH(A30, 'ELI Data File'!A:A, 0))} -> Order Management | C30: {=INDEX('ELI Data File'!J:J, MATCH(A30, 'ELI Data File'!A:A, 0))} -> Approve Order Exceptions & Overrides | D30: {=INDEX('ELI Data File'!M:M, MATCH(A30, 'ELI Data File'!A:A, 0))} -> As Finance, I want to approve or reject exceptions so decisions are explicit and traceable. | E30: {=INDEX('ELI Data File'!H:H, MATCH(A30, 'ELI Data File'!A:A, 0))} -> Finance / Compliance / Admin | F30: =IFERROR(__xludf.DUMMYFUNCTION("AI(""Extract the Goal from the description""&D30)"),"approve or reject exceptions") -> approve or reject exceptions | G30: =IFERROR(__xludf.DUMMYFUNCTION("AI(""Extract the Value from the description""&D30)"),"decisions are explicit and traceable.") -> decisions are explicit and traceable. | H30: {=INDEX('ELI Data File'!D:D, MATCH(A30, 'ELI Data File'!A:A, 0))} -> PH-01 | J30: {=INDEX('ELI Data File'!O:O, MATCH(A30, 'ELI Data File'!A:A, 0))} -> Medium | K30: {=INDEX('ELI Data File'!P:P, MATCH(A30, 'ELI Data File'!A:A, 0))*4} -> 12 | L30: =ROUNDUP(K30*0.2,0) -> 3 | M30: =ROUNDDOWN(SUM(K30:L30)/3,0) -> 5 | N30: =SUM(K30:M30) -> 20
A31: ELI-030 | B31: {=INDEX('ELI Data File'!I:I, MATCH(A31, 'ELI Data File'!A:A, 0))} -> Order Management | C31: {=INDEX('ELI Data File'!J:J, MATCH(A31, 'ELI Data File'!A:A, 0))} -> Approve Order Exceptions & Overrides | D31: {=INDEX('ELI Data File'!M:M, MATCH(A31, 'ELI Data File'!A:A, 0))} -> As Finance, I want an audit trail of approvals so reviews do not rely on email chains. | E31: {=INDEX('ELI Data File'!H:H, MATCH(A31, 'ELI Data File'!A:A, 0))} -> Finance / Compliance / Admin | F31: =IFERROR(__xludf.DUMMYFUNCTION("AI(""Extract the Goal from the description""&D31)"),"view an audit trail of approvals") -> view an audit trail of approvals | G31: =IFERROR(__xludf.DUMMYFUNCTION("AI(""Extract the Value from the description""&D31)"),"reviews do not rely on email chains.") -> reviews do not rely on email chains. | H31: {=INDEX('ELI Data File'!D:D, MATCH(A31, 'ELI Data File'!A:A, 0))} -> PH-01 | J31: {=INDEX('ELI Data File'!O:O, MATCH(A31, 'ELI Data File'!A:A, 0))} -> Medium | K31: {=INDEX('ELI Data File'!P:P, MATCH(A31, 'ELI Data File'!A:A, 0))*4} -> 12 | L31: =ROUNDUP(K31*0.2,0) -> 3 | M31: =ROUNDDOWN(SUM(K31:L31)/3,0) -> 5 | N31: =SUM(K31:M31) -> 20
A32: ELI-031 | B32: {=INDEX('ELI Data File'!I:I, MATCH(A32, 'ELI Data File'!A:A, 0))} -> Fulfillment Orchestration | C32: {=INDEX('ELI Data File'!J:J, MATCH(A32, 'ELI Data File'!A:A, 0))} -> Execute Fulfillment | D32: {=INDEX('ELI Data File'!M:M, MATCH(A32, 'ELI Data File'!A:A, 0))} -> As Ops, I want orders assigned to the appropriate fulfillment resource so execution begins without manual routing. | E32: {=INDEX('ELI Data File'!H:H, MATCH(A32, 'ELI Data File'!A:A, 0))} -> Operations / Order Management | F32: =IFERROR(__xludf.DUMMYFUNCTION("AI(""Extract the Goal from the description""&D32)"),"orders assigned to the appropriate fulfillment resource") -> orders assigned to the appropriate fulfillment resource | G32: =IFERROR(__xludf.DUMMYFUNCTION("AI(""Extract the Value from the description""&D32)"),"execution begins without manual routing.") -> execution begins without manual routing. | H32: {=INDEX('ELI Data File'!D:D, MATCH(A32, 'ELI Data File'!A:A, 0))} -> PH-01 | J32: {=INDEX('ELI Data File'!O:O, MATCH(A32, 'ELI Data File'!A:A, 0))} -> Medium | K32: {=INDEX('ELI Data File'!P:P, MATCH(A32, 'ELI Data File'!A:A, 0))*4} -> 12 | L32: =ROUNDUP(K32*0.2,0) -> 3 | M32: =ROUNDDOWN(SUM(K32:L32)/3,0) -> 5 | N32: =SUM(K32:M32) -> 20
A33: ELI-032 | B33: {=INDEX('ELI Data File'!I:I, MATCH(A33, 'ELI Data File'!A:A, 0))} -> Fulfillment Orchestration | C33: {=INDEX('ELI Data File'!J:J, MATCH(A33, 'ELI Data File'!A:A, 0))} -> Execute Fulfillment | D33: {=INDEX('ELI Data File'!M:M, MATCH(A33, 'ELI Data File'!A:A, 0))} -> As a Warehouse user, I want system-generated pick instructions so I can fulfill orders accurately. | E33: {=INDEX('ELI Data File'!H:H, MATCH(A33, 'ELI Data File'!A:A, 0))} -> Warehouse & Fulfillment | F33: =IFERROR(__xludf.DUMMYFUNCTION("AI(""Extract the Goal from the description""&D33)"),"system-generated pick instructions") -> system-generated pick instructions | G33: =IFERROR(__xludf.DUMMYFUNCTION("AI(""Extract the Value from the description""&D33)"),"fulfill orders accurately.") -> fulfill orders accurately. | H33: {=INDEX('ELI Data File'!D:D, MATCH(A33, 'ELI Data File'!A:A, 0))} -> PH-01 | J33: {=INDEX('ELI Data File'!O:O, MATCH(A33, 'ELI Data File'!A:A, 0))} -> Medium | K33: {=INDEX('ELI Data File'!P:P, MATCH(A33, 'ELI Data File'!A:A, 0))*4} -> 12 | L33: =ROUNDUP(K33*0.2,0) -> 3 | M33: =ROUNDDOWN(SUM(K33:L33)/3,0) -> 5 | N33: =SUM(K33:M33) -> 20
A34: ELI-033 | B34: {=INDEX('ELI Data File'!I:I, MATCH(A34, 'ELI Data File'!A:A, 0))} -> Fulfillment Orchestration | C34: {=INDEX('ELI Data File'!J:J, MATCH(A34, 'ELI Data File'!A:A, 0))} -> Execute Fulfillment | D34: {=INDEX('ELI Data File'!M:M, MATCH(A34, 'ELI Data File'!A:A, 0))} -> As a Warehouse user, I want to pack and ship orders so delivery proceeds according to service levels. | E34: {=INDEX('ELI Data File'!H:H, MATCH(A34, 'ELI Data File'!A:A, 0))} -> Warehouse & Fulfillment | F34: =IFERROR(__xludf.DUMMYFUNCTION("AI(""Extract the Goal from the description""&D34)"),"pack and ship orders") -> pack and ship orders | G34: =IFERROR(__xludf.DUMMYFUNCTION("AI(""Extract the Value from the description""&D34)"),"delivery proceeds according to service levels.") -> delivery proceeds according to service levels. | H34: {=INDEX('ELI Data File'!D:D, MATCH(A34, 'ELI Data File'!A:A, 0))} -> PH-01 | J34: {=INDEX('ELI Data File'!O:O, MATCH(A34, 'ELI Data File'!A:A, 0))} -> Medium | K34: {=INDEX('ELI Data File'!P:P, MATCH(A34, 'ELI Data File'!A:A, 0))*4} -> 12 | L34: =ROUNDUP(K34*0.2,0) -> 3 | M34: =ROUNDDOWN(SUM(K34:L34)/3,0) -> 5 | N34: =SUM(K34:M34) -> 20
A35: ELI-034 | B35: {=INDEX('ELI Data File'!I:I, MATCH(A35, 'ELI Data File'!A:A, 0))} -> Fulfillment Orchestration | C35: {=INDEX('ELI Data File'!J:J, MATCH(A35, 'ELI Data File'!A:A, 0))} -> Determine Fulfillment Routing | D35: {=INDEX('ELI Data File'!M:M, MATCH(A35, 'ELI Data File'!A:A, 0))} -> As Ops, I want the system to select the optimal fulfillment path so cost and SLA requirements are met. | E35: {=INDEX('ELI Data File'!H:H, MATCH(A35, 'ELI Data File'!A:A, 0))} -> Operations / Order Management | F35: =IFERROR(__xludf.DUMMYFUNCTION("AI(""Extract the Goal from the description""&D35)"),"select the optimal fulfillment path") -> select the optimal fulfillment path | G35: =IFERROR(__xludf.DUMMYFUNCTION("AI(""Extract the Value from the description""&D35)"),"cost and SLA requirements are met.") -> cost and SLA requirements are met. | H35: {=INDEX('ELI Data File'!D:D, MATCH(A35, 'ELI Data File'!A:A, 0))} -> PH-01 | J35: {=INDEX('ELI Data File'!O:O, MATCH(A35, 'ELI Data File'!A:A, 0))} -> Medium | K35: {=INDEX('ELI Data File'!P:P, MATCH(A35, 'ELI Data File'!A:A, 0))*4} -> 12 | L35: =ROUNDUP(K35*0.2,0) -> 3 | M35: =ROUNDDOWN(SUM(K35:L35)/3,0) -> 5 | N35: =SUM(K35:M35) -> 20
A36: ELI-035 | B36: {=INDEX('ELI Data File'!I:I, MATCH(A36, 'ELI Data File'!A:A, 0))} -> Fulfillment Orchestration | C36: {=INDEX('ELI Data File'!J:J, MATCH(A36, 'ELI Data File'!A:A, 0))} -> Determine Fulfillment Routing | D36: {=INDEX('ELI Data File'!M:M, MATCH(A36, 'ELI Data File'!A:A, 0))} -> As Ops, I want orders split across sources when necessary so commitments are met. | E36: {=INDEX('ELI Data File'!H:H, MATCH(A36, 'ELI Data File'!A:A, 0))} -> Operations / Order Management | F36: =IFERROR(__xludf.DUMMYFUNCTION("AI(""Extract the Goal from the description""&D36)"),"split orders across sources when necessary") -> split orders across sources when necessary | G36: =IFERROR(__xludf.DUMMYFUNCTION("AI(""Extract the Value from the description""&D36)"),"commitments are met") -> commitments are met | H36: {=INDEX('ELI Data File'!D:D, MATCH(A36, 'ELI Data File'!A:A, 0))} -> PH-01 | J36: {=INDEX('ELI Data File'!O:O, MATCH(A36, 'ELI Data File'!A:A, 0))} -> Medium | K36: {=INDEX('ELI Data File'!P:P, MATCH(A36, 'ELI Data File'!A:A, 0))*4} -> 12 | L36: =ROUNDUP(K36*0.2,0) -> 3 | M36: =ROUNDDOWN(SUM(K36:L36)/3,0) -> 5 | N36: =SUM(K36:M36) -> 20
A37: ELI-036 | B37: {=INDEX('ELI Data File'!I:I, MATCH(A37, 'ELI Data File'!A:A, 0))} -> Fulfillment Orchestration | C37: {=INDEX('ELI Data File'!J:J, MATCH(A37, 'ELI Data File'!A:A, 0))} -> Determine Fulfillment Routing | D37: {=INDEX('ELI Data File'!M:M, MATCH(A37, 'ELI Data File'!A:A, 0))} -> As Finance, I want service-level constraints enforced so contractual obligations are met. | E37: {=INDEX('ELI Data File'!H:H, MATCH(A37, 'ELI Data File'!A:A, 0))} -> Finance / Compliance / Admin | F37: =IFERROR(__xludf.DUMMYFUNCTION("AI(""Extract the Goal from the description""&D37)"),"service-level constraints enforced") -> service-level constraints enforced | G37: =IFERROR(__xludf.DUMMYFUNCTION("AI(""Extract the Value from the description""&D37)"),"contractual obligations are met.") -> contractual obligations are met. | H37: {=INDEX('ELI Data File'!D:D, MATCH(A37, 'ELI Data File'!A:A, 0))} -> PH-01 | J37: {=INDEX('ELI Data File'!O:O, MATCH(A37, 'ELI Data File'!A:A, 0))} -> Medium | K37: {=INDEX('ELI Data File'!P:P, MATCH(A37, 'ELI Data File'!A:A, 0))*4} -> 12 | L37: =ROUNDUP(K37*0.2,0) -> 3 | M37: =ROUNDDOWN(SUM(K37:L37)/3,0) -> 5 | N37: =SUM(K37:M37) -> 20
A38: ELI-037 | B38: {=INDEX('ELI Data File'!I:I, MATCH(A38, 'ELI Data File'!A:A, 0))} -> Fulfillment Orchestration | C38: {=INDEX('ELI Data File'!J:J, MATCH(A38, 'ELI Data File'!A:A, 0))} -> Validate Regulated Substitutions | D38: {=INDEX('ELI Data File'!M:M, MATCH(A38, 'ELI Data File'!A:A, 0))} -> As Ops, I want the system to propose allowed substitutions so I don’t manually assess eligibility. | E38: {=INDEX('ELI Data File'!H:H, MATCH(A38, 'ELI Data File'!A:A, 0))} -> Operations / Order Management | F38: =IFERROR(__xludf.DUMMYFUNCTION("AI(""Extract the Goal from the description""&D38)"),"the system to propose allowed substitutions") -> the system to propose allowed substitutions | G38: =IFERROR(__xludf.DUMMYFUNCTION("AI(""Extract the Value from the description""&D38)"),"I don't manually assess eligibility.") -> I don't manually assess eligibility. | H38: {=INDEX('ELI Data File'!D:D, MATCH(A38, 'ELI Data File'!A:A, 0))} -> PH-01 | J38: {=INDEX('ELI Data File'!O:O, MATCH(A38, 'ELI Data File'!A:A, 0))} -> Medium | K38: {=INDEX('ELI Data File'!P:P, MATCH(A38, 'ELI Data File'!A:A, 0))*4} -> 12 | L38: =ROUNDUP(K38*0.2,0) -> 3 | M38: =ROUNDDOWN(SUM(K38:L38)/3,0) -> 5 | N38: =SUM(K38:M38) -> 20
A39: ELI-038 | B39: {=INDEX('ELI Data File'!I:I, MATCH(A39, 'ELI Data File'!A:A, 0))} -> Fulfillment Orchestration | C39: {=INDEX('ELI Data File'!J:J, MATCH(A39, 'ELI Data File'!A:A, 0))} -> Validate Regulated Substitutions | D39: {=INDEX('ELI Data File'!M:M, MATCH(A39, 'ELI Data File'!A:A, 0))} -> As Compliance, I want vendor certifications validated so non-compliant substitutions are blocked. | E39: {=INDEX('ELI Data File'!H:H, MATCH(A39, 'ELI Data File'!A:A, 0))} -> Finance / Compliance / Admin | F39: =IFERROR(__xludf.DUMMYFUNCTION("AI(""Extract the Goal from the description""&D39)"),"vendor certifications validated") -> vendor certifications validated | G39: =IFERROR(__xludf.DUMMYFUNCTION("AI(""Extract the Value from the description""&D39)"),"non-compliant substitutions are blocked.") -> non-compliant substitutions are blocked. | H39: {=INDEX('ELI Data File'!D:D, MATCH(A39, 'ELI Data File'!A:A, 0))} -> PH-01 | J39: {=INDEX('ELI Data File'!O:O, MATCH(A39, 'ELI Data File'!A:A, 0))} -> Medium | K39: {=INDEX('ELI Data File'!P:P, MATCH(A39, 'ELI Data File'!A:A, 0))*4} -> 12 | L39: =ROUNDUP(K39*0.2,0) -> 3 | M39: =ROUNDDOWN(SUM(K39:L39)/3,0) -> 5 | N39: =SUM(K39:M39) -> 20
A40: ELI-039 | B40: {=INDEX('ELI Data File'!I:I, MATCH(A40, 'ELI Data File'!A:A, 0))} -> Fulfillment Orchestration | C40: {=INDEX('ELI Data File'!J:J, MATCH(A40, 'ELI Data File'!A:A, 0))} -> Validate Regulated Substitutions | D40: {=INDEX('ELI Data File'!M:M, MATCH(A40, 'ELI Data File'!A:A, 0))} -> As Compliance, I want geographic and regulatory rules enforced so orders comply with applicable laws. | E40: {=INDEX('ELI Data File'!H:H, MATCH(A40, 'ELI Data File'!A:A, 0))} -> Finance / Compliance / Admin | F40: =IFERROR(__xludf.DUMMYFUNCTION("AI(""Extract the Goal from the description""&D40)"),"geographic and regulatory rules enforced") -> geographic and regulatory rules enforced | G40: =IFERROR(__xludf.DUMMYFUNCTION("AI(""Extract the Value from the description""&D40)"),"orders comply with applicable laws.") -> orders comply with applicable laws. | H40: {=INDEX('ELI Data File'!D:D, MATCH(A40, 'ELI Data File'!A:A, 0))} -> PH-01 | J40: {=INDEX('ELI Data File'!O:O, MATCH(A40, 'ELI Data File'!A:A, 0))} -> Medium | K40: {=INDEX('ELI Data File'!P:P, MATCH(A40, 'ELI Data File'!A:A, 0))*4} -> 12 | L40: =ROUNDUP(K40*0.2,0) -> 3 | M40: =ROUNDDOWN(SUM(K40:L40)/3,0) -> 5 | N40: =SUM(K40:M40) -> 20
A41: ELI-040 | B41: {=INDEX('ELI Data File'!I:I, MATCH(A41, 'ELI Data File'!A:A, 0))} -> Purchase Management | C41: {=INDEX('ELI Data File'!J:J, MATCH(A41, 'ELI Data File'!A:A, 0))} -> Create Purchase Order | D41: {=INDEX('ELI Data File'!M:M, MATCH(A41, 'ELI Data File'!A:A, 0))} -> As Ops, I want to generate a purchase order from unmet demand so supply gaps are addressed quickly. | E41: {=INDEX('ELI Data File'!H:H, MATCH(A41, 'ELI Data File'!A:A, 0))} -> Operations / Order Management | F41: =IFERROR(__xludf.DUMMYFUNCTION("AI(""Extract the Goal from the description""&D41)"),"generate a purchase order from unmet demand") -> generate a purchase order from unmet demand | G41: =IFERROR(__xludf.DUMMYFUNCTION("AI(""Extract the Value from the description""&D41)"),"supply gaps are addressed quickly.") -> supply gaps are addressed quickly. | H41: {=INDEX('ELI Data File'!D:D, MATCH(A41, 'ELI Data File'!A:A, 0))} -> PH-01 | J41: {=INDEX('ELI Data File'!O:O, MATCH(A41, 'ELI Data File'!A:A, 0))} -> Medium | K41: {=INDEX('ELI Data File'!P:P, MATCH(A41, 'ELI Data File'!A:A, 0))*4} -> 12 | L41: =ROUNDUP(K41*0.2,0) -> 3 | M41: =ROUNDDOWN(SUM(K41:L41)/3,0) -> 5 | N41: =SUM(K41:M41) -> 20
A42: ELI-041 | B42: {=INDEX('ELI Data File'!I:I, MATCH(A42, 'ELI Data File'!A:A, 0))} -> Purchase Management | C42: {=INDEX('ELI Data File'!J:J, MATCH(A42, 'ELI Data File'!A:A, 0))} -> Create Purchase Order | D42: {=INDEX('ELI Data File'!M:M, MATCH(A42, 'ELI Data File'!A:A, 0))} -> As Finance, I want only approved vendors selectable so compliance and pricing terms are enforced. | E42: {=INDEX('ELI Data File'!H:H, MATCH(A42, 'ELI Data File'!A:A, 0))} -> Finance / Compliance / Admin | F42: =IFERROR(__xludf.DUMMYFUNCTION("AI(""Extract the Goal from the description""&D42)"),"only approved vendors selectable") -> only approved vendors selectable | G42: =IFERROR(__xludf.DUMMYFUNCTION("AI(""Extract the Value from the description""&D42)"),"compliance and pricing terms are enforced.") -> compliance and pricing terms are enforced. | H42: {=INDEX('ELI Data File'!D:D, MATCH(A42, 'ELI Data File'!A:A, 0))} -> PH-01 | J42: {=INDEX('ELI Data File'!O:O, MATCH(A42, 'ELI Data File'!A:A, 0))} -> Medium | K42: {=INDEX('ELI Data File'!P:P, MATCH(A42, 'ELI Data File'!A:A, 0))*4} -> 12 | L42: =ROUNDUP(K42*0.2,0) -> 3 | M42: =ROUNDDOWN(SUM(K42:L42)/3,0) -> 5 | N42: =SUM(K42:M42) -> 20
A43: ELI-042 | B43: {=INDEX('ELI Data File'!I:I, MATCH(A43, 'ELI Data File'!A:A, 0))} -> Purchase Management | C43: {=INDEX('ELI Data File'!J:J, MATCH(A43, 'ELI Data File'!A:A, 0))} -> Create Purchase Order | D43: {=INDEX('ELI Data File'!M:M, MATCH(A43, 'ELI Data File'!A:A, 0))} -> As Finance, I want vendor contract terms applied so purchasing aligns with negotiated pricing and penalties. | E43: {=INDEX('ELI Data File'!H:H, MATCH(A43, 'ELI Data File'!A:A, 0))} -> Finance / Compliance / Admin | F43: =IFERROR(__xludf.DUMMYFUNCTION("AI(""Extract the Goal from the description""&D43)"),"apply vendor contract terms") -> apply vendor contract terms | G43: =IFERROR(__xludf.DUMMYFUNCTION("AI(""Extract the Value from the description""&D43)"),"purchasing aligns with negotiated pricing and penalties.") -> purchasing aligns with negotiated pricing and penalties. | H43: {=INDEX('ELI Data File'!D:D, MATCH(A43, 'ELI Data File'!A:A, 0))} -> PH-01 | J43: {=INDEX('ELI Data File'!O:O, MATCH(A43, 'ELI Data File'!A:A, 0))} -> Medium | K43: {=INDEX('ELI Data File'!P:P, MATCH(A43, 'ELI Data File'!A:A, 0))*4} -> 12 | L43: =ROUNDUP(K43*0.2,0) -> 3 | M43: =ROUNDDOWN(SUM(K43:L43)/3,0) -> 5 | N43: =SUM(K43:M43) -> 20
A44: ELI-043 | B44: {=INDEX('ELI Data File'!I:I, MATCH(A44, 'ELI Data File'!A:A, 0))} -> Purchase Management | C44: {=INDEX('ELI Data File'!J:J, MATCH(A44, 'ELI Data File'!A:A, 0))} -> Receive Purchase Order | D44: {=INDEX('ELI Data File'!M:M, MATCH(A44, 'ELI Data File'!A:A, 0))} -> As a Warehouse user, I want to receive goods against a PO so inventory updates accurately. | E44: {=INDEX('ELI Data File'!H:H, MATCH(A44, 'ELI Data File'!A:A, 0))} -> Warehouse & Fulfillment | F44: =IFERROR(__xludf.DUMMYFUNCTION("AI(""Extract the Goal from the description""&D44)"),"receive goods against a PO") -> receive goods against a PO | G44: =IFERROR(__xludf.DUMMYFUNCTION("AI(""Extract the Value from the description""&D44)"),"inventory updates accurately") -> inventory updates accurately | H44: {=INDEX('ELI Data File'!D:D, MATCH(A44, 'ELI Data File'!A:A, 0))} -> PH-01 | J44: {=INDEX('ELI Data File'!O:O, MATCH(A44, 'ELI Data File'!A:A, 0))} -> Medium | K44: {=INDEX('ELI Data File'!P:P, MATCH(A44, 'ELI Data File'!A:A, 0))*4} -> 12 | L44: =ROUNDUP(K44*0.2,0) -> 3 | M44: =ROUNDDOWN(SUM(K44:L44)/3,0) -> 5 | N44: =SUM(K44:M44) -> 20
A45: ELI-044 | B45: {=INDEX('ELI Data File'!I:I, MATCH(A45, 'ELI Data File'!A:A, 0))} -> Purchase Management | C45: {=INDEX('ELI Data File'!J:J, MATCH(A45, 'ELI Data File'!A:A, 0))} -> Receive Purchase Order | D45: {=INDEX('ELI Data File'!M:M, MATCH(A45, 'ELI Data File'!A:A, 0))} -> As a Warehouse user, I want to record partial or over-receipt so discrepancies are tracked. | E45: {=INDEX('ELI Data File'!H:H, MATCH(A45, 'ELI Data File'!A:A, 0))} -> Warehouse & Fulfillment | F45: =IFERROR(__xludf.DUMMYFUNCTION("AI(""Extract the Goal from the description""&D45)"),"record partial or over-receipt") -> record partial or over-receipt | G45: =IFERROR(__xludf.DUMMYFUNCTION("AI(""Extract the Value from the description""&D45)"),"discrepancies are tracked.") -> discrepancies are tracked. | H45: {=INDEX('ELI Data File'!D:D, MATCH(A45, 'ELI Data File'!A:A, 0))} -> PH-01 | J45: {=INDEX('ELI Data File'!O:O, MATCH(A45, 'ELI Data File'!A:A, 0))} -> Medium | K45: {=INDEX('ELI Data File'!P:P, MATCH(A45, 'ELI Data File'!A:A, 0))*4} -> 12 | L45: =ROUNDUP(K45*0.2,0) -> 3 | M45: =ROUNDDOWN(SUM(K45:L45)/3,0) -> 5 | N45: =SUM(K45:M45) -> 20
A46: ELI-045 | B46: {=INDEX('ELI Data File'!I:I, MATCH(A46, 'ELI Data File'!A:A, 0))} -> Purchase Management | C46: {=INDEX('ELI Data File'!J:J, MATCH(A46, 'ELI Data File'!A:A, 0))} -> Receive Purchase Order | D46: {=INDEX('ELI Data File'!M:M, MATCH(A46, 'ELI Data File'!A:A, 0))} -> As Ops, I want POs closed after receipt so purchasing status remains accurate. | E46: {=INDEX('ELI Data File'!H:H, MATCH(A46, 'ELI Data File'!A:A, 0))} -> Operations / Order Management | F46: =IFERROR(__xludf.DUMMYFUNCTION("AI(""Extract the Goal from the description""&D46)"),"POs closed after receipt") -> POs closed after receipt | G46: =IFERROR(__xludf.DUMMYFUNCTION("AI(""Extract the Value from the description""&D46)"),"purchasing status remains accurate.") -> purchasing status remains accurate. | H46: {=INDEX('ELI Data File'!D:D, MATCH(A46, 'ELI Data File'!A:A, 0))} -> PH-01 | J46: {=INDEX('ELI Data File'!O:O, MATCH(A46, 'ELI Data File'!A:A, 0))} -> Medium | K46: {=INDEX('ELI Data File'!P:P, MATCH(A46, 'ELI Data File'!A:A, 0))*4} -> 12 | L46: =ROUNDUP(K46*0.2,0) -> 3 | M46: =ROUNDDOWN(SUM(K46:L46)/3,0) -> 5 | N46: =SUM(K46:M46) -> 20
A47: ELI-046 | B47: {=INDEX('ELI Data File'!I:I, MATCH(A47, 'ELI Data File'!A:A, 0))} -> Purchase Management | C47: {=INDEX('ELI Data File'!J:J, MATCH(A47, 'ELI Data File'!A:A, 0))} -> Source Supply from Vendors | D47: {=INDEX('ELI Data File'!M:M, MATCH(A47, 'ELI Data File'!A:A, 0))} -> As Compliance, I want vendor eligibility evaluated so sourcing complies with certifications and risk policies. | E47: {=INDEX('ELI Data File'!H:H, MATCH(A47, 'ELI Data File'!A:A, 0))} -> Finance / Compliance / Admin | F47: =IFERROR(__xludf.DUMMYFUNCTION("AI(""Extract the Goal from the description""&D47)"),"vendor eligibility evaluated") -> vendor eligibility evaluated | G47: =IFERROR(__xludf.DUMMYFUNCTION("AI(""Extract the Value from the description""&D47)"),"sourcing complies with certifications and risk policies.") -> sourcing complies with certifications and risk policies. | H47: {=INDEX('ELI Data File'!D:D, MATCH(A47, 'ELI Data File'!A:A, 0))} -> PH-01 | J47: {=INDEX('ELI Data File'!O:O, MATCH(A47, 'ELI Data File'!A:A, 0))} -> Medium | K47: {=INDEX('ELI Data File'!P:P, MATCH(A47, 'ELI Data File'!A:A, 0))*4} -> 12 | L47: =ROUNDUP(K47*0.2,0) -> 3 | M47: =ROUNDDOWN(SUM(K47:L47)/3,0) -> 5 | N47: =SUM(K47:M47) -> 20
A48: ELI-047 | B48: {=INDEX('ELI Data File'!I:I, MATCH(A48, 'ELI Data File'!A:A, 0))} -> Purchase Management | C48: {=INDEX('ELI Data File'!J:J, MATCH(A48, 'ELI Data File'!A:A, 0))} -> Source Supply from Vendors | D48: {=INDEX('ELI Data File'!M:M, MATCH(A48, 'ELI Data File'!A:A, 0))} -> As Ops, I want to compare vendor lead times and SLAs so sourcing decisions meet fulfillment needs. | E48: {=INDEX('ELI Data File'!H:H, MATCH(A48, 'ELI Data File'!A:A, 0))} -> Operations / Order Management | F48: =IFERROR(__xludf.DUMMYFUNCTION("AI(""Extract the Goal from the description""&D48)"),"compare vendor lead times and SLAs") -> compare vendor lead times and SLAs | G48: =IFERROR(__xludf.DUMMYFUNCTION("AI(""Extract the Value from the description""&D48)"),"sourcing decisions meet fulfillment needs.") -> sourcing decisions meet fulfillment needs. | H48: {=INDEX('ELI Data File'!D:D, MATCH(A48, 'ELI Data File'!A:A, 0))} -> PH-01 | J48: {=INDEX('ELI Data File'!O:O, MATCH(A48, 'ELI Data File'!A:A, 0))} -> Medium | K48: {=INDEX('ELI Data File'!P:P, MATCH(A48, 'ELI Data File'!A:A, 0))*4} -> 12 | L48: =ROUNDUP(K48*0.2,0) -> 3 | M48: =ROUNDDOWN(SUM(K48:L48)/3,0) -> 5 | N48: =SUM(K48:M48) -> 20
A49: ELI-048 | B49: {=INDEX('ELI Data File'!I:I, MATCH(A49, 'ELI Data File'!A:A, 0))} -> Purchase Management | C49: {=INDEX('ELI Data File'!J:J, MATCH(A49, 'ELI Data File'!A:A, 0))} -> Source Supply from Vendors | D49: {=INDEX('ELI Data File'!M:M, MATCH(A49, 'ELI Data File'!A:A, 0))} -> As Ops, I want the system to select the optimal vendor so cost, compliance, and delivery goals are balanced. | E49: {=INDEX('ELI Data File'!H:H, MATCH(A49, 'ELI Data File'!A:A, 0))} -> Operations / Order Management | F49: =IFERROR(__xludf.DUMMYFUNCTION("AI(""Extract the Goal from the description""&D49)"),"select the optimal vendor") -> select the optimal vendor | G49: =IFERROR(__xludf.DUMMYFUNCTION("AI(""Extract the Value from the description""&D49)"),"cost, compliance, and delivery goals are balanced.") -> cost, compliance, and delivery goals are balanced. | H49: {=INDEX('ELI Data File'!D:D, MATCH(A49, 'ELI Data File'!A:A, 0))} -> PH-01 | J49: {=INDEX('ELI Data File'!O:O, MATCH(A49, 'ELI Data File'!A:A, 0))} -> Medium | K49: {=INDEX('ELI Data File'!P:P, MATCH(A49, 'ELI Data File'!A:A, 0))*4} -> 12 | L49: =ROUNDUP(K49*0.2,0) -> 3 | M49: =ROUNDDOWN(SUM(K49:L49)/3,0) -> 5 | N49: =SUM(K49:M49) -> 20
A50: ELI-049 | B50: {=INDEX('ELI Data File'!I:I, MATCH(A50, 'ELI Data File'!A:A, 0))} -> Sales Order Processing | C50: {=INDEX('ELI Data File'!J:J, MATCH(A50, 'ELI Data File'!A:A, 0))} -> Sales Order Processing | D50: {=INDEX('ELI Data File'!M:M, MATCH(A50, 'ELI Data File'!A:A, 0))} -> Capture order header and lines tied to a customer context. | E50: {=INDEX('ELI Data File'!H:H, MATCH(A50, 'ELI Data File'!A:A, 0))} -> N/A | F50: =IFERROR(__xludf.DUMMYFUNCTION("AI(""Extract the Goal from the description""&D50)"),"Capture order header and lines tied to a customer context.") -> Capture order header and lines tied to a customer context. | G50: =IFERROR(__xludf.DUMMYFUNCTION("AI(""Extract the Value from the description""&D50)"),"This description does not follow the standard ""As a... I want to... so I can..."" format. The goal of this story is ""Capture order header and lines tied to a customer context."" Since there is no ""so I can"" clause, I cannot extract the value.") -> This description does not follow the standard "As a... I want to... so I can..." format. The goal of this story is "Capture order header and lines tied to a customer context." Since there is no "so I can" clause, I cannot extract the value. | H50: {=INDEX('ELI Data File'!D:D, MATCH(A50, 'ELI Data File'!A:A, 0))} -> PH-01 | J50: {=INDEX('ELI Data File'!O:O, MATCH(A50, 'ELI Data File'!A:A, 0))} -> Medium | K50: {=INDEX('ELI Data File'!P:P, MATCH(A50, 'ELI Data File'!A:A, 0))*4} -> 20 | L50: =ROUNDUP(K50*0.2,0) -> 4 | M50: =ROUNDDOWN(SUM(K50:L50)/3,0) -> 8 | N50: =SUM(K50:M50) -> 32
A51: ELI-050 | B51: {=INDEX('ELI Data File'!I:I, MATCH(A51, 'ELI Data File'!A:A, 0))} -> Sales Order Processing | C51: {=INDEX('ELI Data File'!J:J, MATCH(A51, 'ELI Data File'!A:A, 0))} -> Sales Order Processing | D51: {=INDEX('ELI Data File'!M:M, MATCH(A51, 'ELI Data File'!A:A, 0))} -> Resolve active contract(s) and customer compliance requirements for this order. | E51: {=INDEX('ELI Data File'!H:H, MATCH(A51, 'ELI Data File'!A:A, 0))} -> N/A | F51: =IFERROR(__xludf.DUMMYFUNCTION("AI(""Extract the Goal from the description""&D51)"),"Resolve active contract(s) and customer compliance requirements for this order.") -> Resolve active contract(s) and customer compliance requirements for this order. | G51: =IFERROR(__xludf.DUMMYFUNCTION("AI(""Extract the Value from the description""&D51)"),"Ensure terms are consistent and auditable, and non-compliant orders are blocked.") -> Ensure terms are consistent and auditable, and non-compliant orders are blocked. | H51: {=INDEX('ELI Data File'!D:D, MATCH(A51, 'ELI Data File'!A:A, 0))} -> PH-01 | J51: {=INDEX('ELI Data File'!O:O, MATCH(A51, 'ELI Data File'!A:A, 0))} -> High | K51: {=INDEX('ELI Data File'!P:P, MATCH(A51, 'ELI Data File'!A:A, 0))*4} -> 32 | L51: =ROUNDUP(K51*0.2,0) -> 7 | M51: =ROUNDDOWN(SUM(K51:L51)/3,0) -> 13 | N51: =SUM(K51:M51) -> 52
A52: ELI-051 | B52: {=INDEX('ELI Data File'!I:I, MATCH(A52, 'ELI Data File'!A:A, 0))} -> Sales Order Processing | C52: {=INDEX('ELI Data File'!J:J, MATCH(A52, 'ELI Data File'!A:A, 0))} -> Sales Order Processing | D52: {=INDEX('ELI Data File'!M:M, MATCH(A52, 'ELI Data File'!A:A, 0))} -> Apply tiered pricing, rebates/penalties, and ensure terms are consistent and auditable. | E52: {=INDEX('ELI Data File'!H:H, MATCH(A52, 'ELI Data File'!A:A, 0))} -> N/A | F52: =IFERROR(__xludf.DUMMYFUNCTION("AI(""Extract the Goal from the description""&D52)"),"Apply tiered pricing, rebates/penalties, and ensure terms are consistent and auditable.") -> Apply tiered pricing, rebates/penalties, and ensure terms are consistent and auditable. | G52: =IFERROR(__xludf.DUMMYFUNCTION("AI(""Extract the Value from the description""&D52)"),"ensure terms are consistent and auditable.") -> ensure terms are consistent and auditable. | H52: {=INDEX('ELI Data File'!D:D, MATCH(A52, 'ELI Data File'!A:A, 0))} -> PH-01 | J52: {=INDEX('ELI Data File'!O:O, MATCH(A52, 'ELI Data File'!A:A, 0))} -> High | K52: {=INDEX('ELI Data File'!P:P, MATCH(A52, 'ELI Data File'!A:A, 0))*4} -> 32 | L52: =ROUNDUP(K52*0.2,0) -> 7 | M52: =ROUNDDOWN(SUM(K52:L52)/3,0) -> 13 | N52: =SUM(K52:M52) -> 52
A53: ELI-052 | B53: {=INDEX('ELI Data File'!I:I, MATCH(A53, 'ELI Data File'!A:A, 0))} -> Sales Order Processing | C53: {=INDEX('ELI Data File'!J:J, MATCH(A53, 'ELI Data File'!A:A, 0))} -> Sales Order Processing | D53: {=INDEX('ELI Data File'!M:M, MATCH(A53, 'ELI Data File'!A:A, 0))} -> Identify orders requiring approval and route to Finance/Admin for decision. | E53: {=INDEX('ELI Data File'!H:H, MATCH(A53, 'ELI Data File'!A:A, 0))} -> N/A | F53: =IFERROR(__xludf.DUMMYFUNCTION("AI(""Extract the Goal from the description""&D53)"),"Identify orders requiring approval and route to Finance/Admin for decision.") -> Identify orders requiring approval and route to Finance/Admin for decision. | G53: =IFERROR(__xludf.DUMMYFUNCTION("AI(""Extract the Value from the description""&D53)"),"for decision.") -> for decision. | H53: {=INDEX('ELI Data File'!D:D, MATCH(A53, 'ELI Data File'!A:A, 0))} -> PH-01 | J53: {=INDEX('ELI Data File'!O:O, MATCH(A53, 'ELI Data File'!A:A, 0))} -> Medium | K53: {=INDEX('ELI Data File'!P:P, MATCH(A53, 'ELI Data File'!A:A, 0))*4} -> 20 | L53: =ROUNDUP(K53*0.2,0) -> 4 | M53: =ROUNDDOWN(SUM(K53:L53)/3,0) -> 8 | N53: =SUM(K53:M53) -> 32
A54: ELI-053 | B54: {=INDEX('ELI Data File'!I:I, MATCH(A54, 'ELI Data File'!A:A, 0))} -> Sales Order Processing | C54: {=INDEX('ELI Data File'!J:J, MATCH(A54, 'ELI Data File'!A:A, 0))} -> Sales Order Processing | D54: {=INDEX('ELI Data File'!M:M, MATCH(A54, 'ELI Data File'!A:A, 0))} -> Transition approved orders to a fulfillment-ready state and emit downstream signals. | E54: {=INDEX('ELI Data File'!H:H, MATCH(A54, 'ELI Data File'!A:A, 0))} -> N/A | F54: =IFERROR(__xludf.DUMMYFUNCTION("AI(""Extract the Goal from the description""&D54)"),"Transition approved orders to a fulfillment-ready state and emit downstream signals.") -> Transition approved orders to a fulfillment-ready state and emit downstream signals. | G54: =IFERROR(__xludf.DUMMYFUNCTION("AI(""Extract the Value from the description""&D54)"),"emit downstream signals") -> emit downstream signals | H54: {=INDEX('ELI Data File'!D:D, MATCH(A54, 'ELI Data File'!A:A, 0))} -> PH-01 | J54: {=INDEX('ELI Data File'!O:O, MATCH(A54, 'ELI Data File'!A:A, 0))} -> Medium | K54: {=INDEX('ELI Data File'!P:P, MATCH(A54, 'ELI Data File'!A:A, 0))*4} -> 20 | L54: =ROUNDUP(K54*0.2,0) -> 4 | M54: =ROUNDDOWN(SUM(K54:L54)/3,0) -> 8 | N54: =SUM(K54:M54) -> 32
A55: ELI-054 | B55: {=INDEX('ELI Data File'!I:I, MATCH(A55, 'ELI Data File'!A:A, 0))} -> Fulfillment Execution | C55: {=INDEX('ELI Data File'!J:J, MATCH(A55, 'ELI Data File'!A:A, 0))} -> Fulfillment Execution | D55: {=INDEX('ELI Data File'!M:M, MATCH(A55, 'ELI Data File'!A:A, 0))} -> Choose warehouse/vendor sources and split the order when needed to meet SLAs and rules. | E55: {=INDEX('ELI Data File'!H:H, MATCH(A55, 'ELI Data File'!A:A, 0))} -> N/A | F55: =IFERROR(__xludf.DUMMYFUNCTION("AI(""Extract the Goal from the description""&D55)"),"Choose warehouse/vendor sources and split the order when needed") -> Choose warehouse/vendor sources and split the order when needed | G55: =IFERROR(__xludf.DUMMYFUNCTION("AI(""Extract the Value from the description""&D55)"),"meet SLAs and rules.") -> meet SLAs and rules. | H55: {=INDEX('ELI Data File'!D:D, MATCH(A55, 'ELI Data File'!A:A, 0))} -> PH-01 | J55: {=INDEX('ELI Data File'!O:O, MATCH(A55, 'ELI Data File'!A:A, 0))} -> High | K55: {=INDEX('ELI Data File'!P:P, MATCH(A55, 'ELI Data File'!A:A, 0))*4} -> 32 | L55: =ROUNDUP(K55*0.2,0) -> 7 | M55: =ROUNDDOWN(SUM(K55:L55)/3,0) -> 13 | N55: =SUM(K55:M55) -> 52
A56: ELI-055 | B56: {=INDEX('ELI Data File'!I:I, MATCH(A56, 'ELI Data File'!A:A, 0))} -> Fulfillment Execution | C56: {=INDEX('ELI Data File'!J:J, MATCH(A56, 'ELI Data File'!A:A, 0))} -> Fulfillment Execution | D56: {=INDEX('ELI Data File'!M:M, MATCH(A56, 'ELI Data File'!A:A, 0))} -> Reserve inventory for the chosen sources and prevent double-allocation. | E56: {=INDEX('ELI Data File'!H:H, MATCH(A56, 'ELI Data File'!A:A, 0))} -> N/A | F56: =IFERROR(__xludf.DUMMYFUNCTION("AI(""Extract the Goal from the description""&D56)"),"Reserve inventory for the chosen sources and prevent double-allocation.") -> Reserve inventory for the chosen sources and prevent double-allocation. | G56: =IFERROR(__xludf.DUMMYFUNCTION("AI(""Extract the Value from the description""&D56)"),"prevent double-allocation.") -> prevent double-allocation. | H56: {=INDEX('ELI Data File'!D:D, MATCH(A56, 'ELI Data File'!A:A, 0))} -> PH-01 | J56: {=INDEX('ELI Data File'!O:O, MATCH(A56, 'ELI Data File'!A:A, 0))} -> High | K56: {=INDEX('ELI Data File'!P:P, MATCH(A56, 'ELI Data File'!A:A, 0))*4} -> 32 | L56: =ROUNDUP(K56*0.2,0) -> 7 | M56: =ROUNDDOWN(SUM(K56:L56)/3,0) -> 13 | N56: =SUM(K56:M56) -> 52
A57: ELI-056 | B57: {=INDEX('ELI Data File'!I:I, MATCH(A57, 'ELI Data File'!A:A, 0))} -> Fulfillment Execution | C57: {=INDEX('ELI Data File'!J:J, MATCH(A57, 'ELI Data File'!A:A, 0))} -> Fulfillment Execution | D57: {=INDEX('ELI Data File'!M:M, MATCH(A57, 'ELI Data File'!A:A, 0))} -> Validate substitutions against contracts, certifications, and geographic/regulatory constraints. | E57: {=INDEX('ELI Data File'!H:H, MATCH(A57, 'ELI Data File'!A:A, 0))} -> N/A | F57: =IFERROR(__xludf.DUMMYFUNCTION("AI(""Extract the Goal from the description""&D57)"),"Validate substitutions against contracts, certifications, and geographic/regulatory constraints.") -> Validate substitutions against contracts, certifications, and geographic/regulatory constraints. | G57: =IFERROR(__xludf.DUMMYFUNCTION("AI(""Extract the Value from the description""&D57)"),"ensure compliance with contracts, certifications, and geographic/regulatory constraints.") -> ensure compliance with contracts, certifications, and geographic/regulatory constraints. | H57: {=INDEX('ELI Data File'!D:D, MATCH(A57, 'ELI Data File'!A:A, 0))} -> PH-01 | J57: {=INDEX('ELI Data File'!O:O, MATCH(A57, 'ELI Data File'!A:A, 0))} -> High | K57: {=INDEX('ELI Data File'!P:P, MATCH(A57, 'ELI Data File'!A:A, 0))*4} -> 32 | L57: =ROUNDUP(K57*0.2,0) -> 7 | M57: =ROUNDDOWN(SUM(K57:L57)/3,0) -> 13 | N57: =SUM(K57:M57) -> 52
A58: ELI-057 | B58: {=INDEX('ELI Data File'!I:I, MATCH(A58, 'ELI Data File'!A:A, 0))} -> Fulfillment Execution | C58: {=INDEX('ELI Data File'!J:J, MATCH(A58, 'ELI Data File'!A:A, 0))} -> Fulfillment Execution | D58: {=INDEX('ELI Data File'!M:M, MATCH(A58, 'ELI Data File'!A:A, 0))} -> Produce actionable fulfillment instructions for warehouse execution. | E58: {=INDEX('ELI Data File'!H:H, MATCH(A58, 'ELI Data File'!A:A, 0))} -> N/A | F58: =IFERROR(__xludf.DUMMYFUNCTION("AI(""Extract the Goal from the description""&D58)"),"Produce actionable fulfillment instructions") -> Produce actionable fulfillment instructions | G58: =IFERROR(__xludf.DUMMYFUNCTION("AI(""Extract the Value from the description""&D58)"),"for warehouse execution.") -> for warehouse execution. | H58: {=INDEX('ELI Data File'!D:D, MATCH(A58, 'ELI Data File'!A:A, 0))} -> PH-01 | J58: {=INDEX('ELI Data File'!O:O, MATCH(A58, 'ELI Data File'!A:A, 0))} -> Medium | K58: {=INDEX('ELI Data File'!P:P, MATCH(A58, 'ELI Data File'!A:A, 0))*4} -> 20 | L58: =ROUNDUP(K58*0.2,0) -> 4 | M58: =ROUNDDOWN(SUM(K58:L58)/3,0) -> 8 | N58: =SUM(K58:M58) -> 32
A59: ELI-058 | B59: {=INDEX('ELI Data File'!I:I, MATCH(A59, 'ELI Data File'!A:A, 0))} -> Fulfillment Execution | C59: {=INDEX('ELI Data File'!J:J, MATCH(A59, 'ELI Data File'!A:A, 0))} -> Fulfillment Execution | D59: {=INDEX('ELI Data File'!M:M, MATCH(A59, 'ELI Data File'!A:A, 0))} -> Mark shipments dispatched, attach tracking, and update order lifecycle state. | E59: {=INDEX('ELI Data File'!H:H, MATCH(A59, 'ELI Data File'!A:A, 0))} -> N/A | F59: =IFERROR(__xludf.DUMMYFUNCTION("AI(""Extract the Goal from the description""&D59)"),"Mark shipments dispatched, attach tracking, and update order lifecycle state.") -> Mark shipments dispatched, attach tracking, and update order lifecycle state. | G59: =IFERROR(__xludf.DUMMYFUNCTION("AI(""Extract the Value from the description""&D59)"),"Efficient and accurate tracking of the order through its lifecycle.") -> Efficient and accurate tracking of the order through its lifecycle. | H59: {=INDEX('ELI Data File'!D:D, MATCH(A59, 'ELI Data File'!A:A, 0))} -> PH-01 | J59: {=INDEX('ELI Data File'!O:O, MATCH(A59, 'ELI Data File'!A:A, 0))} -> Medium | K59: {=INDEX('ELI Data File'!P:P, MATCH(A59, 'ELI Data File'!A:A, 0))*4} -> 20 | L59: =ROUNDUP(K59*0.2,0) -> 4 | M59: =ROUNDDOWN(SUM(K59:L59)/3,0) -> 8 | N59: =SUM(K59:M59) -> 32
A60: ELI-059 | B60: {=INDEX('ELI Data File'!I:I, MATCH(A60, 'ELI Data File'!A:A, 0))} -> Purchase Replenishment | C60: {=INDEX('ELI Data File'!J:J, MATCH(A60, 'ELI Data File'!A:A, 0))} -> Purchase Replenishment | D60: {=INDEX('ELI Data File'!M:M, MATCH(A60, 'ELI Data File'!A:A, 0))} -> Identify when demand exceeds available inventory and triggers purchasing. | E60: {=INDEX('ELI Data File'!H:H, MATCH(A60, 'ELI Data File'!A:A, 0))} -> N/A | F60: =IFERROR(__xludf.DUMMYFUNCTION("AI(""Extract the Goal from the description""&D60)"),"Identify when demand exceeds available inventory and triggers purchasing.") -> Identify when demand exceeds available inventory and triggers purchasing. | G60: =IFERROR(__xludf.DUMMYFUNCTION("AI(""Extract the Value from the description""&D60)"),"triggers purchasing") -> triggers purchasing | H60: {=INDEX('ELI Data File'!D:D, MATCH(A60, 'ELI Data File'!A:A, 0))} -> PH-01 | J60: {=INDEX('ELI Data File'!O:O, MATCH(A60, 'ELI Data File'!A:A, 0))} -> Medium | K60: {=INDEX('ELI Data File'!P:P, MATCH(A60, 'ELI Data File'!A:A, 0))*4} -> 20 | L60: =ROUNDUP(K60*0.2,0) -> 4 | M60: =ROUNDDOWN(SUM(K60:L60)/3,0) -> 8 | N60: =SUM(K60:M60) -> 32
A61: ELI-060 | B61: {=INDEX('ELI Data File'!I:I, MATCH(A61, 'ELI Data File'!A:A, 0))} -> Purchase Replenishment | C61: {=INDEX('ELI Data File'!J:J, MATCH(A61, 'ELI Data File'!A:A, 0))} -> Purchase Replenishment | D61: {=INDEX('ELI Data File'!M:M, MATCH(A61, 'ELI Data File'!A:A, 0))} -> Ensure vendor eligibility and select optimal vendor based on lead times and rules. | E61: {=INDEX('ELI Data File'!H:H, MATCH(A61, 'ELI Data File'!A:A, 0))} -> N/A | F61: =IFERROR(__xludf.DUMMYFUNCTION("AI(""Extract the Goal from the description""&D61)"),"Ensure vendor eligibility and select optimal vendor based on lead times and rules.") -> Ensure vendor eligibility and select optimal vendor based on lead times and rules. | G61: =IFERROR(__xludf.DUMMYFUNCTION("AI(""Extract the Value from the description""&D61)"),"based on lead times and rules.") -> based on lead times and rules. | H61: {=INDEX('ELI Data File'!D:D, MATCH(A61, 'ELI Data File'!A:A, 0))} -> PH-01 | J61: {=INDEX('ELI Data File'!O:O, MATCH(A61, 'ELI Data File'!A:A, 0))} -> Medium | K61: {=INDEX('ELI Data File'!P:P, MATCH(A61, 'ELI Data File'!A:A, 0))*4} -> 20 | L61: =ROUNDUP(K61*0.2,0) -> 4 | M61: =ROUNDDOWN(SUM(K61:L61)/3,0) -> 8 | N61: =SUM(K61:M61) -> 32
A62: ELI-061 | B62: {=INDEX('ELI Data File'!I:I, MATCH(A62, 'ELI Data File'!A:A, 0))} -> Purchase Replenishment | C62: {=INDEX('ELI Data File'!J:J, MATCH(A62, 'ELI Data File'!A:A, 0))} -> Purchase Replenishment | D62: {=INDEX('ELI Data File'!M:M, MATCH(A62, 'ELI Data File'!A:A, 0))} -> Create PO with applied vendor contract terms and required delivery dates. | E62: {=INDEX('ELI Data File'!H:H, MATCH(A62, 'ELI Data File'!A:A, 0))} -> N/A | F62: =IFERROR(__xludf.DUMMYFUNCTION("AI(""Extract the Goal from the description""&D62)"),"Create PO with applied vendor contract terms and required delivery dates.") -> Create PO with applied vendor contract terms and required delivery dates. | G62: =IFERROR(__xludf.DUMMYFUNCTION("AI(""Extract the Value from the description""&D62)"),"applied vendor contract terms and required delivery dates") -> applied vendor contract terms and required delivery dates | H62: {=INDEX('ELI Data File'!D:D, MATCH(A62, 'ELI Data File'!A:A, 0))} -> PH-01 | J62: {=INDEX('ELI Data File'!O:O, MATCH(A62, 'ELI Data File'!A:A, 0))} -> Medium | K62: {=INDEX('ELI Data File'!P:P, MATCH(A62, 'ELI Data File'!A:A, 0))*4} -> 20 | L62: =ROUNDUP(K62*0.2,0) -> 4 | M62: =ROUNDDOWN(SUM(K62:L62)/3,0) -> 8 | N62: =SUM(K62:M62) -> 32
A63: ELI-062 | B63: {=INDEX('ELI Data File'!I:I, MATCH(A63, 'ELI Data File'!A:A, 0))} -> Inventory / WMS Service | C63: {=INDEX('ELI Data File'!J:J, MATCH(A63, 'ELI Data File'!A:A, 0))} -> Inventory / WMS Service | D63: {=INDEX('ELI Data File'!M:M, MATCH(A63, 'ELI Data File'!A:A, 0))} -> Source of truth for on-hand/available inventory and the execution surface for reservations and receiving updates. | E63: {=INDEX('ELI Data File'!H:H, MATCH(A63, 'ELI Data File'!A:A, 0))} -> N/A | F63: =IFERROR(__xludf.DUMMYFUNCTION("AI(""Extract the Goal from the description""&D63)"),"be the source of truth for on-hand/available inventory and the execution surface for reservations and receiving updates") -> be the source of truth for on-hand/available inventory and the execution surface for reservations and receiving updates | G63: =IFERROR(__xludf.DUMMYFUNCTION("AI(""Extract the Value from the description""&D63)"),"on-hand/available inventory and the execution surface for reservations and receiving updates.") -> on-hand/available inventory and the execution surface for reservations and receiving updates. | H63: {=INDEX('ELI Data File'!D:D, MATCH(A63, 'ELI Data File'!A:A, 0))} -> PH-01 | J63: {=INDEX('ELI Data File'!O:O, MATCH(A63, 'ELI Data File'!A:A, 0))} -> High | K63: {=INDEX('ELI Data File'!P:P, MATCH(A63, 'ELI Data File'!A:A, 0))*4} -> 32 | L63: =ROUNDUP(K63*0.2,0) -> 7 | M63: =ROUNDDOWN(SUM(K63:L63)/3,0) -> 13 | N63: =SUM(K63:M63) -> 52
A64: ELI-063 | B64: {=INDEX('ELI Data File'!I:I, MATCH(A64, 'ELI Data File'!A:A, 0))} -> Vendor Portal / Supplier API | C64: {=INDEX('ELI Data File'!J:J, MATCH(A64, 'ELI Data File'!A:A, 0))} -> Vendor Portal / Supplier API | D64: {=INDEX('ELI Data File'!M:M, MATCH(A64, 'ELI Data File'!A:A, 0))} -> External vendor system(s) providing item availability, lead times, SLAs, and certification status for sourcing and substitution decisions. | E64: {=INDEX('ELI Data File'!H:H, MATCH(A64, 'ELI Data File'!A:A, 0))} -> N/A | F64: =IFERROR(__xludf.DUMMYFUNCTION("AI(""Extract the Goal from the description""&D64)"),"Provide item availability, lead times, SLAs, and certification status for sourcing and substitution decisions") -> Provide item availability, lead times, SLAs, and certification status for sourcing and substitution decisions | G64: =IFERROR(__xludf.DUMMYFUNCTION("AI(""Extract the Value from the description""&D64)"),"for sourcing and substitution decisions.") -> for sourcing and substitution decisions. | H64: {=INDEX('ELI Data File'!D:D, MATCH(A64, 'ELI Data File'!A:A, 0))} -> PH-01 | J64: {=INDEX('ELI Data File'!O:O, MATCH(A64, 'ELI Data File'!A:A, 0))} -> High | K64: {=INDEX('ELI Data File'!P:P, MATCH(A64, 'ELI Data File'!A:A, 0))*4} -> 32 | L64: =ROUNDUP(K64*0.2,0) -> 7 | M64: =ROUNDDOWN(SUM(K64:L64)/3,0) -> 13 | N64: =SUM(K64:M64) -> 52
A65: ELI-064 | B65: {=INDEX('ELI Data File'!I:I, MATCH(A65, 'ELI Data File'!A:A, 0))} -> Compliance Rules & Restrictions Service | C65: {=INDEX('ELI Data File'!J:J, MATCH(A65, 'ELI Data File'!A:A, 0))} -> Compliance Rules & Restrictions Service | D65: {=INDEX('ELI Data File'!M:M, MATCH(A65, 'ELI Data File'!A:A, 0))} -> External or internal service that returns compliance rules, geo restrictions, and item-level regulatory attributes for evaluation at order and substitution time. | E65: {=INDEX('ELI Data File'!H:H, MATCH(A65, 'ELI Data File'!A:A, 0))} -> N/A | F65: =IFERROR(__xludf.DUMMYFUNCTION("AI(""Extract the Goal from the description""&D65)"),"returns compliance rules, geo restrictions, and item-level regulatory attributes for evaluation at order and substitution time.") -> returns compliance rules, geo restrictions, and item-level regulatory attributes for evaluation at order and substitution time. | G65: =IFERROR(__xludf.DUMMYFUNCTION("AI(""Extract the Value from the description""&D65)"),"evaluation at order and substitution time.") -> evaluation at order and substitution time. | H65: {=INDEX('ELI Data File'!D:D, MATCH(A65, 'ELI Data File'!A:A, 0))} -> PH-01 | J65: {=INDEX('ELI Data File'!O:O, MATCH(A65, 'ELI Data File'!A:A, 0))} -> High | K65: {=INDEX('ELI Data File'!P:P, MATCH(A65, 'ELI Data File'!A:A, 0))*4} -> 32 | L65: =ROUNDUP(K65*0.2,0) -> 7 | M65: =ROUNDDOWN(SUM(K65:L65)/3,0) -> 13 | N65: =SUM(K65:M65) -> 52
A66: ELI-065 | B66: {=INDEX('ELI Data File'!I:I, MATCH(A66, 'ELI Data File'!A:A, 0))} -> Messaging / Event Bus | C66: {=INDEX('ELI Data File'!J:J, MATCH(A66, 'ELI Data File'!A:A, 0))} -> Messaging / Event Bus | D66: {=INDEX('ELI Data File'!M:M, MATCH(A66, 'ELI Data File'!A:A, 0))} -> Central eventing platform used to publish OMS domain events for consumers (ERP integration workers, dashboards, notifications). | E66: {=INDEX('ELI Data File'!H:H, MATCH(A66, 'ELI Data File'!A:A, 0))} -> N/A | F66: =IFERROR(__xludf.DUMMYFUNCTION("AI(""Extract the Goal from the description""&D66)"),"publish OMS domain events for consumers (ERP integration workers, dashboards, notifications)") -> publish OMS domain events for consumers (ERP integration workers, dashboards, notifications) | G66: =IFERROR(__xludf.DUMMYFUNCTION("AI(""Extract the Value from the description""&D66)"),"consumers (ERP integration workers, dashboards, notifications)") -> consumers (ERP integration workers, dashboards, notifications) | H66: {=INDEX('ELI Data File'!D:D, MATCH(A66, 'ELI Data File'!A:A, 0))} -> PH-01 | J66: {=INDEX('ELI Data File'!O:O, MATCH(A66, 'ELI Data File'!A:A, 0))} -> Medium | K66: {=INDEX('ELI Data File'!P:P, MATCH(A66, 'ELI Data File'!A:A, 0))*4} -> 20 | L66: =ROUNDUP(K66*0.2,0) -> 4 | M66: =ROUNDDOWN(SUM(K66:L66)/3,0) -> 8 | N66: =SUM(K66:M66) -> 32
A67: ELI-066 | B67: {=INDEX('ELI Data File'!I:I, MATCH(A67, 'ELI Data File'!A:A, 0))} -> Foundations | C67: {=INDEX('ELI Data File'!J:J, MATCH(A67, 'ELI Data File'!A:A, 0))} -> Navigation and Component Library | D67: {=INDEX('ELI Data File'!M:M, MATCH(A67, 'ELI Data File'!A:A, 0))} -> Choose and install a design system | E67: {=INDEX('ELI Data File'!H:H, MATCH(A67, 'ELI Data File'!A:A, 0))} -> N/A | F67: =IFERROR(__xludf.DUMMYFUNCTION("AI(""Extract the Goal from the description""&D67)"),"Choose and install a design system") -> Choose and install a design system | G67: =IFERROR(__xludf.DUMMYFUNCTION("AI(""Extract the Value from the description""&D67)"),"This description does not contain a specific ""so I can"" value/outcome.") -> This description does not contain a specific "so I can" value/outcome. | H67: {=INDEX('ELI Data File'!D:D, MATCH(A67, 'ELI Data File'!A:A, 0))} -> PH-01 | J67: {=INDEX('ELI Data File'!O:O, MATCH(A67, 'ELI Data File'!A:A, 0))} -> Medium | K67: {=INDEX('ELI Data File'!P:P, MATCH(A67, 'ELI Data File'!A:A, 0))*4} -> 20 | L67: =ROUNDUP(K67*0.2,0) -> 4 | M67: =ROUNDDOWN(SUM(K67:L67)/3,0) -> 8 | N67: =SUM(K67:M67) -> 32
A68: ELI-067 | B68: {=INDEX('ELI Data File'!I:I, MATCH(A68, 'ELI Data File'!A:A, 0))} -> Foundations | C68: {=INDEX('ELI Data File'!J:J, MATCH(A68, 'ELI Data File'!A:A, 0))} -> Navigation and Component Library | D68: {=INDEX('ELI Data File'!M:M, MATCH(A68, 'ELI Data File'!A:A, 0))} -> Define dashboard shell, sidebar, headers, and modal containers. | E68: {=INDEX('ELI Data File'!H:H, MATCH(A68, 'ELI Data File'!A:A, 0))} -> N/A | F68: =IFERROR(__xludf.DUMMYFUNCTION("AI(""Extract the Goal from the description""&D68)"),"define dashboard shell, sidebar, headers, and modal containers") -> define dashboard shell, sidebar, headers, and modal containers | G68: =IFERROR(__xludf.DUMMYFUNCTION("AI(""Extract the Value from the description""&D68)"),"No explicit value is stated.") -> No explicit value is stated. | H68: {=INDEX('ELI Data File'!D:D, MATCH(A68, 'ELI Data File'!A:A, 0))} -> PH-01 | J68: {=INDEX('ELI Data File'!O:O, MATCH(A68, 'ELI Data File'!A:A, 0))} -> Medium | K68: {=INDEX('ELI Data File'!P:P, MATCH(A68, 'ELI Data File'!A:A, 0))*4} -> 20 | L68: =ROUNDUP(K68*0.2,0) -> 4 | M68: =ROUNDDOWN(SUM(K68:L68)/3,0) -> 8 | N68: =SUM(K68:M68) -> 32
A69: ELI-068 | B69: {=INDEX('ELI Data File'!I:I, MATCH(A69, 'ELI Data File'!A:A, 0))} -> Foundations | C69: {=INDEX('ELI Data File'!J:J, MATCH(A69, 'ELI Data File'!A:A, 0))} -> Navigation and Component Library | D69: {=INDEX('ELI Data File'!M:M, MATCH(A69, 'ELI Data File'!A:A, 0))} -> Set up route configuration and page access logic | E69: {=INDEX('ELI Data File'!H:H, MATCH(A69, 'ELI Data File'!A:A, 0))} -> N/A | F69: =IFERROR(__xludf.DUMMYFUNCTION("AI(""Extract the Goal from the description""&D69)"),"Set up route configuration and page access logic") -> Set up route configuration and page access logic | G69: =IFERROR(__xludf.DUMMYFUNCTION("AI(""Extract the Value from the description""&D69)"),"application can function correctly and securely") -> application can function correctly and securely | H69: {=INDEX('ELI Data File'!D:D, MATCH(A69, 'ELI Data File'!A:A, 0))} -> PH-01 | J69: {=INDEX('ELI Data File'!O:O, MATCH(A69, 'ELI Data File'!A:A, 0))} -> Medium | K69: {=INDEX('ELI Data File'!P:P, MATCH(A69, 'ELI Data File'!A:A, 0))*4} -> 20 | L69: =ROUNDUP(K69*0.2,0) -> 4 | M69: =ROUNDDOWN(SUM(K69:L69)/3,0) -> 8 | N69: =SUM(K69:M69) -> 32
A70: ELI-069 | B70: {=INDEX('ELI Data File'!I:I, MATCH(A70, 'ELI Data File'!A:A, 0))} -> Foundations | C70: {=INDEX('ELI Data File'!J:J, MATCH(A70, 'ELI Data File'!A:A, 0))} -> User Management | D70: {=INDEX('ELI Data File'!M:M, MATCH(A70, 'ELI Data File'!A:A, 0))} -> Define core fields like name, email, auth method, and settings. | E70: {=INDEX('ELI Data File'!H:H, MATCH(A70, 'ELI Data File'!A:A, 0))} -> N/A | F70: =IFERROR(__xludf.DUMMYFUNCTION("AI(""Extract the Goal from the description""&D70)"),"Define core fields like name, email, auth method, and settings.") -> Define core fields like name, email, auth method, and settings. | G70: =IFERROR(__xludf.DUMMYFUNCTION("AI(""Extract the Value from the description""&D70)"),"The description itself is the goal (to define core fields). There is no explicit ""so I can"" value statement in the description provided. If this is a technical task, the value is inherent in setting up the foundational data structure for users.") -> The description itself is the goal (to define core fields). There is no explicit "so I can" value statement in the description provided. If this is a technical task, the value is inherent in setting up the foundational data structure for users. | H70: {=INDEX('ELI Data File'!D:D, MATCH(A70, 'ELI Data File'!A:A, 0))} -> PH-01 | J70: {=INDEX('ELI Data File'!O:O, MATCH(A70, 'ELI Data File'!A:A, 0))} -> Medium | K70: {=INDEX('ELI Data File'!P:P, MATCH(A70, 'ELI Data File'!A:A, 0))*4} -> 20 | L70: =ROUNDUP(K70*0.2,0) -> 4 | M70: =ROUNDDOWN(SUM(K70:L70)/3,0) -> 8 | N70: =SUM(K70:M70) -> 32
A71: ELI-070 | B71: {=INDEX('ELI Data File'!I:I, MATCH(A71, 'ELI Data File'!A:A, 0))} -> Foundations | C71: {=INDEX('ELI Data File'!J:J, MATCH(A71, 'ELI Data File'!A:A, 0))} -> User Management | D71: {=INDEX('ELI Data File'!M:M, MATCH(A71, 'ELI Data File'!A:A, 0))} -> Allow users to update their information, timezone, and avatar. | E71: {=INDEX('ELI Data File'!H:H, MATCH(A71, 'ELI Data File'!A:A, 0))} -> N/A | F71: =IFERROR(__xludf.DUMMYFUNCTION("AI(""Extract the Goal from the description""&D71)"),"Allow users to update their information, timezone, and avatar.") -> Allow users to update their information, timezone, and avatar. | G71: =IFERROR(__xludf.DUMMYFUNCTION("AI(""Extract the Value from the description""&D71)"),"Extracting the ""so I can"" value from the phrase ""Allow users to update their information, timezone, and avatar"" does not produce a meaningful benefit as it stands alone and is not a complete user story following the ""As a... I want... so I can..."" f"&"ormat. I will assume the intended request is to extract the goal, which is the action the user wants to perform. users update their information, timezone, and avatar") -> Extracting the "so I can" value from the phrase "Allow users to update their information, timezone, and avatar" does not produce a meaningful benefit as it stands alone and is not a complete user story following the "As a... I want... so I can..." format. I will assume the intended request is to extract the goal, which is the action the user wants to perform. users update their information, timezone, and avatar | H71: {=INDEX('ELI Data File'!D:D, MATCH(A71, 'ELI Data File'!A:A, 0))} -> PH-01 | J71: {=INDEX('ELI Data File'!O:O, MATCH(A71, 'ELI Data File'!A:A, 0))} -> Low | K71: {=INDEX('ELI Data File'!P:P, MATCH(A71, 'ELI Data File'!A:A, 0))*4} -> 12 | L71: =ROUNDUP(K71*0.2,0) -> 3 | M71: =ROUNDDOWN(SUM(K71:L71)/3,0) -> 5 | N71: =SUM(K71:M71) -> 20
A72: ELI-071 | B72: {=INDEX('ELI Data File'!I:I, MATCH(A72, 'ELI Data File'!A:A, 0))} -> Foundations | C72: {=INDEX('ELI Data File'!J:J, MATCH(A72, 'ELI Data File'!A:A, 0))} -> User Management | D72: {=INDEX('ELI Data File'!M:M, MATCH(A72, 'ELI Data File'!A:A, 0))} -> Log login history, session duration, and access activity. | E72: {=INDEX('ELI Data File'!H:H, MATCH(A72, 'ELI Data File'!A:A, 0))} -> N/A | F72: =IFERROR(__xludf.DUMMYFUNCTION("AI(""Extract the Goal from the description""&D72)"),"Log login history, session duration, and access activity.") -> Log login history, session duration, and access activity. | G72: =IFERROR(__xludf.DUMMYFUNCTION("AI(""Extract the Value from the description""&D72)"),"No explicit value is stated in the provided text, as it describes the action itself.") -> No explicit value is stated in the provided text, as it describes the action itself. | H72: {=INDEX('ELI Data File'!D:D, MATCH(A72, 'ELI Data File'!A:A, 0))} -> PH-01 | J72: {=INDEX('ELI Data File'!O:O, MATCH(A72, 'ELI Data File'!A:A, 0))} -> Medium | K72: {=INDEX('ELI Data File'!P:P, MATCH(A72, 'ELI Data File'!A:A, 0))*4} -> 20 | L72: =ROUNDUP(K72*0.2,0) -> 4 | M72: =ROUNDDOWN(SUM(K72:L72)/3,0) -> 8 | N72: =SUM(K72:M72) -> 32
A73: ELI-072 | B73: {=INDEX('ELI Data File'!I:I, MATCH(A73, 'ELI Data File'!A:A, 0))} -> Foundations | C73: {=INDEX('ELI Data File'!J:J, MATCH(A73, 'ELI Data File'!A:A, 0))} -> Authentication & Security | D73: {=INDEX('ELI Data File'!M:M, MATCH(A73, 'ELI Data File'!A:A, 0))} -> Integrate platforms like Auth0, Clerk, or Firebase Auth. | E73: {=INDEX('ELI Data File'!H:H, MATCH(A73, 'ELI Data File'!A:A, 0))} -> N/A | F73: =IFERROR(__xludf.DUMMYFUNCTION("AI(""Extract the Goal from the description""&D73)"),"Integrate platforms like Auth0, Clerk, or Firebase Auth.") -> Integrate platforms like Auth0, Clerk, or Firebase Auth. | G73: =IFERROR(__xludf.DUMMYFUNCTION("AI(""Extract the Value from the description""&D73)"),"Ensure a secure and robust authentication system.") -> Ensure a secure and robust authentication system. | H73: {=INDEX('ELI Data File'!D:D, MATCH(A73, 'ELI Data File'!A:A, 0))} -> PH-01 | J73: {=INDEX('ELI Data File'!O:O, MATCH(A73, 'ELI Data File'!A:A, 0))} -> Medium | K73: {=INDEX('ELI Data File'!P:P, MATCH(A73, 'ELI Data File'!A:A, 0))*4} -> 20 | L73: =ROUNDUP(K73*0.2,0) -> 4 | M73: =ROUNDDOWN(SUM(K73:L73)/3,0) -> 8 | N73: =SUM(K73:M73) -> 32
A74: ELI-073 | B74: {=INDEX('ELI Data File'!I:I, MATCH(A74, 'ELI Data File'!A:A, 0))} -> Foundations | C74: {=INDEX('ELI Data File'!J:J, MATCH(A74, 'ELI Data File'!A:A, 0))} -> Authentication & Security | D74: {=INDEX('ELI Data File'!M:M, MATCH(A74, 'ELI Data File'!A:A, 0))} -> Use JWTs or sessions to authorize requests on protected endpoints. | E74: {=INDEX('ELI Data File'!H:H, MATCH(A74, 'ELI Data File'!A:A, 0))} -> N/A | F74: =IFERROR(__xludf.DUMMYFUNCTION("AI(""Extract the Goal from the description""&D74)"),"authorize requests on protected endpoints") -> authorize requests on protected endpoints | G74: =IFERROR(__xludf.DUMMYFUNCTION("AI(""Extract the Value from the description""&D74)"),"authorize requests on protected endpoints") -> authorize requests on protected endpoints | H74: {=INDEX('ELI Data File'!D:D, MATCH(A74, 'ELI Data File'!A:A, 0))} -> PH-01 | J74: {=INDEX('ELI Data File'!O:O, MATCH(A74, 'ELI Data File'!A:A, 0))} -> High | K74: {=INDEX('ELI Data File'!P:P, MATCH(A74, 'ELI Data File'!A:A, 0))*4} -> 32 | L74: =ROUNDUP(K74*0.2,0) -> 7 | M74: =ROUNDDOWN(SUM(K74:L74)/3,0) -> 13 | N74: =SUM(K74:M74) -> 52
A75: ELI-074 | B75: {=INDEX('ELI Data File'!I:I, MATCH(A75, 'ELI Data File'!A:A, 0))} -> Foundations | C75: {=INDEX('ELI Data File'!J:J, MATCH(A75, 'ELI Data File'!A:A, 0))} -> Authentication & Security | D75: {=INDEX('ELI Data File'!M:M, MATCH(A75, 'ELI Data File'!A:A, 0))} -> Encrypt sensitive data both in transit (HTTPS) and at rest (AES). | E75: {=INDEX('ELI Data File'!H:H, MATCH(A75, 'ELI Data File'!A:A, 0))} -> N/A | F75: =IFERROR(__xludf.DUMMYFUNCTION("AI(""Extract the Goal from the description""&D75)"),"Encrypt sensitive data both in transit (HTTPS) and at rest (AES).") -> Encrypt sensitive data both in transit (HTTPS) and at rest (AES). | G75: =IFERROR(__xludf.DUMMYFUNCTION("AI(""Extract the Value from the description""&D75)"),"To protect sensitive data and ensure security.") -> To protect sensitive data and ensure security. | H75: {=INDEX('ELI Data File'!D:D, MATCH(A75, 'ELI Data File'!A:A, 0))} -> PH-01 | J75: {=INDEX('ELI Data File'!O:O, MATCH(A75, 'ELI Data File'!A:A, 0))} -> High | K75: {=INDEX('ELI Data File'!P:P, MATCH(A75, 'ELI Data File'!A:A, 0))*4} -> 32 | L75: =ROUNDUP(K75*0.2,0) -> 7 | M75: =ROUNDDOWN(SUM(K75:L75)/3,0) -> 13 | N75: =SUM(K75:M75) -> 52
A76: ELI-075 | B76: {=INDEX('ELI Data File'!I:I, MATCH(A76, 'ELI Data File'!A:A, 0))} -> Foundations | C76: {=INDEX('ELI Data File'!J:J, MATCH(A76, 'ELI Data File'!A:A, 0))} -> Data Management | D76: {=INDEX('ELI Data File'!M:M, MATCH(A76, 'ELI Data File'!A:A, 0))} -> Model core data object of the system | E76: {=INDEX('ELI Data File'!H:H, MATCH(A76, 'ELI Data File'!A:A, 0))} -> N/A | F76: =IFERROR(__xludf.DUMMYFUNCTION("AI(""Extract the Goal from the description""&D76)"),"Model core data object of the system") -> Model core data object of the system | G76: =IFERROR(__xludf.DUMMYFUNCTION("AI(""Extract the Value from the description""&D76)"),"Model core data object of the system") -> Model core data object of the system | H76: {=INDEX('ELI Data File'!D:D, MATCH(A76, 'ELI Data File'!A:A, 0))} -> PH-01 | J76: {=INDEX('ELI Data File'!O:O, MATCH(A76, 'ELI Data File'!A:A, 0))} -> High | K76: {=INDEX('ELI Data File'!P:P, MATCH(A76, 'ELI Data File'!A:A, 0))*4} -> 32 | L76: =ROUNDUP(K76*0.2,0) -> 7 | M76: =ROUNDDOWN(SUM(K76:L76)/3,0) -> 13 | N76: =SUM(K76:M76) -> 52
A77: ELI-076 | B77: {=INDEX('ELI Data File'!I:I, MATCH(A77, 'ELI Data File'!A:A, 0))} -> Foundations | C77: {=INDEX('ELI Data File'!J:J, MATCH(A77, 'ELI Data File'!A:A, 0))} -> Data Management | D77: {=INDEX('ELI Data File'!M:M, MATCH(A77, 'ELI Data File'!A:A, 0))} -> Expose backend endpoints for accessing and modifying | E77: {=INDEX('ELI Data File'!H:H, MATCH(A77, 'ELI Data File'!A:A, 0))} -> N/A | F77: =IFERROR(__xludf.DUMMYFUNCTION("AI(""Extract the Goal from the description""&D77)"),"expose backend endpoints for accessing and modifying") -> expose backend endpoints for accessing and modifying | G77: =IFERROR(__xludf.DUMMYFUNCTION("AI(""Extract the Value from the description""&D77)"),"for accessing and modifying") -> for accessing and modifying | H77: {=INDEX('ELI Data File'!D:D, MATCH(A77, 'ELI Data File'!A:A, 0))} -> PH-01 | J77: {=INDEX('ELI Data File'!O:O, MATCH(A77, 'ELI Data File'!A:A, 0))} -> Medium | K77: {=INDEX('ELI Data File'!P:P, MATCH(A77, 'ELI Data File'!A:A, 0))*4} -> 20 | L77: =ROUNDUP(K77*0.2,0) -> 4 | M77: =ROUNDDOWN(SUM(K77:L77)/3,0) -> 8 | N77: =SUM(K77:M77) -> 32
A78: ELI-077 | B78: {=INDEX('ELI Data File'!I:I, MATCH(A78, 'ELI Data File'!A:A, 0))} -> Foundations | C78: {=INDEX('ELI Data File'!J:J, MATCH(A78, 'ELI Data File'!A:A, 0))} -> Data Management | D78: {=INDEX('ELI Data File'!M:M, MATCH(A78, 'ELI Data File'!A:A, 0))} -> Capture a change log for critical actions like edits, deletions, or merges. | E78: {=INDEX('ELI Data File'!H:H, MATCH(A78, 'ELI Data File'!A:A, 0))} -> N/A | F78: =IFERROR(__xludf.DUMMYFUNCTION("AI(""Extract the Goal from the description""&D78)"),"Capture a change log for critical actions like edits, deletions, or merges.") -> Capture a change log for critical actions like edits, deletions, or merges. | G78: =IFERROR(__xludf.DUMMYFUNCTION("AI(""Extract the Value from the description""&D78)"),"This description appears to be missing the ""as the"" and ""so I can"" structure. Based on the provided description, ""Capture a change log for critical actions like edits, deletions, or merges."", the value is implied to be for auditing or data integrity"&". I am unable to accurately extract the value when the user story format is not present in the description.") -> This description appears to be missing the "as the" and "so I can" structure. Based on the provided description, "Capture a change log for critical actions like edits, deletions, or merges.", the value is implied to be for auditing or data integrity. I am unable to accurately extract the value when the user story format is not present in the description. | H78: {=INDEX('ELI Data File'!D:D, MATCH(A78, 'ELI Data File'!A:A, 0))} -> PH-01 | J78: {=INDEX('ELI Data File'!O:O, MATCH(A78, 'ELI Data File'!A:A, 0))} -> High | K78: {=INDEX('ELI Data File'!P:P, MATCH(A78, 'ELI Data File'!A:A, 0))*4} -> 32 | L78: =ROUNDUP(K78*0.2,0) -> 7 | M78: =ROUNDDOWN(SUM(K78:L78)/3,0) -> 13 | N78: =SUM(K78:M78) -> 52
A79: ELI-078 | B79: {=INDEX('ELI Data File'!I:I, MATCH(A79, 'ELI Data File'!A:A, 0))} -> Foundations | C79: {=INDEX('ELI Data File'!J:J, MATCH(A79, 'ELI Data File'!A:A, 0))} -> Backend Infrastructure | D79: {=INDEX('ELI Data File'!M:M, MATCH(A79, 'ELI Data File'!A:A, 0))} -> Centralize request routing, versioning, throttling, and request/response transformations for REST/GraphQL. | E79: {=INDEX('ELI Data File'!H:H, MATCH(A79, 'ELI Data File'!A:A, 0))} -> N/A | F79: =IFERROR(__xludf.DUMMYFUNCTION("AI(""Extract the Goal from the description""&D79)"),"Centralize request routing, versioning, throttling, and request/response transformations for REST/GraphQL") -> Centralize request routing, versioning, throttling, and request/response transformations for REST/GraphQL | G79: =IFERROR(__xludf.DUMMYFUNCTION("AI(""Extract the Value from the description""&D79)"),"efficiently manage and scale API traffic") -> efficiently manage and scale API traffic | H79: {=INDEX('ELI Data File'!D:D, MATCH(A79, 'ELI Data File'!A:A, 0))} -> PH-01 | J79: {=INDEX('ELI Data File'!O:O, MATCH(A79, 'ELI Data File'!A:A, 0))} -> Medium | K79: {=INDEX('ELI Data File'!P:P, MATCH(A79, 'ELI Data File'!A:A, 0))*4} -> 20 | L79: =ROUNDUP(K79*0.2,0) -> 4 | M79: =ROUNDDOWN(SUM(K79:L79)/3,0) -> 8 | N79: =SUM(K79:M79) -> 32
A80: ELI-079 | B80: {=INDEX('ELI Data File'!I:I, MATCH(A80, 'ELI Data File'!A:A, 0))} -> Foundations | C80: {=INDEX('ELI Data File'!J:J, MATCH(A80, 'ELI Data File'!A:A, 0))} -> Backend Infrastructure | D80: {=INDEX('ELI Data File'!M:M, MATCH(A80, 'ELI Data File'!A:A, 0))} -> Support async jobs, scheduled work, and event-driven workflows (e.g., retries, dead-letter queues). | E80: {=INDEX('ELI Data File'!H:H, MATCH(A80, 'ELI Data File'!A:A, 0))} -> N/A | F80: =IFERROR(__xludf.DUMMYFUNCTION("AI(""Extract the Goal from the description""&D80)"),"Support async jobs, scheduled work, and event-driven workflows (e.g., retries, dead-letter queues).") -> Support async jobs, scheduled work, and event-driven workflows (e.g., retries, dead-letter queues). | G80: =IFERROR(__xludf.DUMMYFUNCTION("AI(""Extract the Value from the description""&D80)"),"e.g., retries, dead-letter queues.") -> e.g., retries, dead-letter queues. | H80: {=INDEX('ELI Data File'!D:D, MATCH(A80, 'ELI Data File'!A:A, 0))} -> PH-01 | J80: {=INDEX('ELI Data File'!O:O, MATCH(A80, 'ELI Data File'!A:A, 0))} -> High | K80: {=INDEX('ELI Data File'!P:P, MATCH(A80, 'ELI Data File'!A:A, 0))*4} -> 32 | L80: =ROUNDUP(K80*0.2,0) -> 7 | M80: =ROUNDDOWN(SUM(K80:L80)/3,0) -> 13 | N80: =SUM(K80:M80) -> 52
A81: ELI-080 | B81: {=INDEX('ELI Data File'!I:I, MATCH(A81, 'ELI Data File'!A:A, 0))} -> Foundations | C81: {=INDEX('ELI Data File'!J:J, MATCH(A81, 'ELI Data File'!A:A, 0))} -> Backend Infrastructure | D81: {=INDEX('ELI Data File'!M:M, MATCH(A81, 'ELI Data File'!A:A, 0))} -> Collect logs, metrics, and traces with correlation IDs and alerting thresholds. | E81: {=INDEX('ELI Data File'!H:H, MATCH(A81, 'ELI Data File'!A:A, 0))} -> N/A | F81: =IFERROR(__xludf.DUMMYFUNCTION("AI(""Extract the Goal from the description""&D81)"),"collect logs, metrics, and traces with correlation IDs and alerting thresholds") -> collect logs, metrics, and traces with correlation IDs and alerting thresholds | G81: =IFERROR(__xludf.DUMMYFUNCTION("AI(""Extract the Value from the description""&D81)"),"with correlation IDs and alerting thresholds.") -> with correlation IDs and alerting thresholds. | H81: {=INDEX('ELI Data File'!D:D, MATCH(A81, 'ELI Data File'!A:A, 0))} -> PH-01 | J81: {=INDEX('ELI Data File'!O:O, MATCH(A81, 'ELI Data File'!A:A, 0))} -> Medium | K81: {=INDEX('ELI Data File'!P:P, MATCH(A81, 'ELI Data File'!A:A, 0))*4} -> 20 | L81: =ROUNDUP(K81*0.2,0) -> 4 | M81: =ROUNDDOWN(SUM(K81:L81)/3,0) -> 8 | N81: =SUM(K81:M81) -> 32
A82: ELI-081 | B82: {=INDEX('ELI Data File'!I:I, MATCH(A82, 'ELI Data File'!A:A, 0))} -> Foundations | C82: {=INDEX('ELI Data File'!J:J, MATCH(A82, 'ELI Data File'!A:A, 0))} -> DevOps | D82: {=INDEX('ELI Data File'!M:M, MATCH(A82, 'ELI Data File'!A:A, 0))} -> Use .env files and secrets management for tokens, keys, and DB strings. | E82: {=INDEX('ELI Data File'!H:H, MATCH(A82, 'ELI Data File'!A:A, 0))} -> N/A | F82: =IFERROR(__xludf.DUMMYFUNCTION("AI(""Extract the Goal from the description""&D82)"),"Use .env files and secrets management for tokens, keys, and DB strings.") -> Use .env files and secrets management for tokens, keys, and DB strings. | G82: =IFERROR(__xludf.DUMMYFUNCTION("AI(""Extract the Value from the description""&D82)"),"Ensure sensitive data is protected and deployment is secure.") -> Ensure sensitive data is protected and deployment is secure. | H82: {=INDEX('ELI Data File'!D:D, MATCH(A82, 'ELI Data File'!A:A, 0))} -> PH-01 | J82: {=INDEX('ELI Data File'!O:O, MATCH(A82, 'ELI Data File'!A:A, 0))} -> Medium | K82: {=INDEX('ELI Data File'!P:P, MATCH(A82, 'ELI Data File'!A:A, 0))*4} -> 20 | L82: =ROUNDUP(K82*0.2,0) -> 4 | M82: =ROUNDDOWN(SUM(K82:L82)/3,0) -> 8 | N82: =SUM(K82:M82) -> 32
A83: ELI-082 | B83: {=INDEX('ELI Data File'!I:I, MATCH(A83, 'ELI Data File'!A:A, 0))} -> Foundations | C83: {=INDEX('ELI Data File'!J:J, MATCH(A83, 'ELI Data File'!A:A, 0))} -> DevOps | D83: {=INDEX('ELI Data File'!M:M, MATCH(A83, 'ELI Data File'!A:A, 0))} -> Deploy with GitHub Actions, Vercel, or custom workflows for build/test/release. | E83: {=INDEX('ELI Data File'!H:H, MATCH(A83, 'ELI Data File'!A:A, 0))} -> N/A | F83: =IFERROR(__xludf.DUMMYFUNCTION("AI(""Extract the Goal from the description""&D83)"),"Deploy with GitHub Actions, Vercel, or custom workflows for build/test/release.") -> Deploy with GitHub Actions, Vercel, or custom workflows for build/test/release. | G83: =IFERROR(__xludf.DUMMYFUNCTION("AI(""Extract the Value from the description""&D83)"),"for build/test/release.") -> for build/test/release. | H83: {=INDEX('ELI Data File'!D:D, MATCH(A83, 'ELI Data File'!A:A, 0))} -> PH-01 | J83: {=INDEX('ELI Data File'!O:O, MATCH(A83, 'ELI Data File'!A:A, 0))} -> Medium | K83: {=INDEX('ELI Data File'!P:P, MATCH(A83, 'ELI Data File'!A:A, 0))*4} -> 20 | L83: =ROUNDUP(K83*0.2,0) -> 4 | M83: =ROUNDDOWN(SUM(K83:L83)/3,0) -> 8 | N83: =SUM(K83:M83) -> 32
A84: ELI-083 | B84: {=INDEX('ELI Data File'!I:I, MATCH(A84, 'ELI Data File'!A:A, 0))} -> Foundations | C84: {=INDEX('ELI Data File'!J:J, MATCH(A84, 'ELI Data File'!A:A, 0))} -> DevOps | D84: {=INDEX('ELI Data File'!M:M, MATCH(A84, 'ELI Data File'!A:A, 0))} -> Integrate unit, integration, and end-to-end test pipelines. | E84: {=INDEX('ELI Data File'!H:H, MATCH(A84, 'ELI Data File'!A:A, 0))} -> N/A | F84: =IFERROR(__xludf.DUMMYFUNCTION("AI(""Extract the Goal from the description""&D84)"),"Integrate unit, integration, and end-to-end test pipelines.") -> Integrate unit, integration, and end-to-end test pipelines. | G84: =IFERROR(__xludf.DUMMYFUNCTION("AI(""Extract the Value from the description""&D84)"),"The description ""Integrate unit, integration, and end-to-end test pipelines."" is a technical task and does not explicitly state the value/benefit.") -> The description "Integrate unit, integration, and end-to-end test pipelines." is a technical task and does not explicitly state the value/benefit. | H84: {=INDEX('ELI Data File'!D:D, MATCH(A84, 'ELI Data File'!A:A, 0))} -> PH-01 | J84: {=INDEX('ELI Data File'!O:O, MATCH(A84, 'ELI Data File'!A:A, 0))} -> Medium | K84: {=INDEX('ELI Data File'!P:P, MATCH(A84, 'ELI Data File'!A:A, 0))*4} -> 20 | L84: =ROUNDUP(K84*0.2,0) -> 4 | M84: =ROUNDDOWN(SUM(K84:L84)/3,0) -> 8 | N84: =SUM(K84:M84) -> 32
N99: =SUM(K99:M99) -> 0
N100: =SUM(K100:M100) -> 0
N101: =SUM(K101:M101) -> 0
N102: =SUM(K102:M102) -> 0
N103: =SUM(K103:M103) -> 0
N104: =SUM(K104:M104) -> 0
N105: =SUM(K105:M105) -> 0
N106: =SUM(K106:M106) -> 0
N107: =SUM(K107:M107) -> 0
N108: =SUM(K108:M108) -> 0
N109: =SUM(K109:M109) -> 0
N110: =SUM(K110:M110) -> 0
... N187: =SUM(K187:M187) -> 0

Sheet ELI Data File
A1: ELI ID | B1: Strategy Ref | C1: Blueprint Ref | D1: Phase Ref ID | E1: Deliverable ID | F1: Epic ID | G1: User Group ID | H1: User Group Name | I1: Deliverable Name | J1: Epic Name | K1: ELI Name | L1: ELI Type | M1: ELI Description | N1: Notes | O1: Complexity | P1: Effort | Q1: Tech Hours | R1: SA Hours
A2: ELI-001 | B2: FUNC-001 | C2: BP-1765865704672 | D2: PH-01 | E2: DEL-001 | F2: EPIC-010 | H2: Sales / Account Management | I2: Customer Management | J2: Manage Customers | K2: Create a Customer Profile | L2: User Story | M2: As a Sales user, I want to create a customer profile so that orders can be associated with the correct legal and billing entity. | O2: Medium | P2: 3 | Q2: 4 | R2: =Q2*0.2 -> 0.8
A3: ELI-002 | B3: FUNC-001 | C3: BP-1765865704672 | D3: PH-01 | E3: DEL-001 | F3: EPIC-010 | H3: Sales / Account Management | I3: Customer Management | J3: Manage Customers | K3: Update Customer Information | L3: User Story | M3: As a Sales user, I want to update customer details so changes are reflected in future orders. | O3: Medium | P3: 3 | Q3: 4 | R3: =Q3*0.2 -> 0.8
A4: ELI-003 | B4: FUNC-001 | C4: BP-1765865704672 | D4: PH-01 | E4: DEL-001 | F4: EPIC-010 | H4: Operations / Order Management | I4: Customer Management | J4: Manage Customers | K4: Search and Retrieve Customers | L4: User Story | M4: As an Ops user, I want to search customers quickly so I can validate order context without manual lookup. | O4: Medium | P4: 3 | Q4: 4 | R4: =Q4*0.2 -> 0.8
A5: ELI-004 | B5: FUNC-002 | C5: BP-1765865704672 | D5: PH-01 | E5: DEL-001 | F5: EPIC-011 | H5: Finance / Compliance / Admin | I5: Customer Management | J5: Associate Contracts to Customers | K5: Link Active Contract to Customer | L5: User Story | M5: As an Admin, I want to associate an active contract to a customer so pricing and terms are enforced at order time. | O5: Medium | P5: 3 | R5: =Q5*0.2 -> 0
A6: ELI-005 | B6: FUNC-002 | C6: BP-1765865704672 | D6: PH-01 | E6: DEL-001 | F6: EPIC-011 | H6: Finance / Compliance / Admin | I6: Customer Management | J6: Associate Contracts to Customers | K6: Prevent Orders Without Active Contracts | L6: User Story | M6: As Finance, I want to prevent orders for customers without active contracts to avoid uncontrolled pricing. | O6: Medium | P6: 3 | R6: =Q6*0.2 -> 0
A7: ELI-006 | B7: FUNC-002 | C7: BP-1765865704672 | D7: PH-01 | E7: DEL-001 | F7: EPIC-011 | H7: Finance / Compliance / Admin | I7: Customer Management | J7: Associate Contracts to Customers | K7: View Contract Association History | L7: User Story | M7: As Finance, I want to view contract assignment history so audits do not rely on spreadsheets. | O7: Medium | P7: 3 | R7: =Q7*0.2 -> 0
A8: ELI-007 | B8: FUNC-003 | C8: BP-1765865704672 | D8: PH-01 | E8: DEL-001 | F8: EPIC-012 | H8: Finance / Compliance / Admin | I8: Customer Management | J8: Manage Customer Compliance Requirements | K8: Define Customer Compliance Constraints | L8: User Story | M8: As a Compliance admin, I want to define customer-specific compliance rules so non-compliant orders are blocked. | O8: Medium | P8: 3 | R8: =Q8*0.2 -> 0
A9: ELI-008 | B9: FUNC-003 | C9: BP-1765865704672 | D9: PH-01 | E9: DEL-001 | F9: EPIC-012 | H9: Operations / Order Management | I9: Customer Management | J9: Manage Customer Compliance Requirements | K9: Apply Compliance Rules at Order Time | L9: User Story | M9: As Ops, I want compliance rules evaluated automatically so I don’t interpret regulations manually. | O9: Medium | P9: 3 | R9: =Q9*0.2 -> 0
A10: ELI-009 | B10: FUNC-003 | C10: BP-1765865704672 | D10: PH-01 | E10: DEL-001 | F10: EPIC-012 | H10: Finance / Compliance / Admin | I10: Customer Management | J10: Manage Customer Compliance Requirements | K10: Audit Customer Compliance Decisions | L10: User Story | M10: As Compliance, I want an audit trail of compliance decisions so regulatory reviews are defensible. | O10: Medium | P10: 3 | R10: =Q10*0.2 -> 0
A11: ELI-010 | B11: FUNC-004 | C11: BP-1765865704672 | D11: PH-01 | E11: DEL-002 | F11: EPIC-013 | H11: Operations / Order Management | I11: Inventory Management | J11: Manage Inventory | K11: View Real-Time Inventory Levels | L11: User Story | M11: As an Ops user, I want to view real-time inventory levels so I can make accurate fulfillment decisions. | O11: Medium | P11: 3 | R11: =Q11*0.2 -> 0
A12: ELI-011 | B12: FUNC-004 | C12: BP-1765865704672 | D12: PH-01 | E12: DEL-002 | F12: EPIC-013 | H12: Warehouse & Fulfillment | I12: Inventory Management | J12: Manage Inventory | K12: Adjust Inventory Quantity | L12: User Story | M12: As a Warehouse user, I want to adjust inventory quantities so physical discrepancies are reflected in the system. | O12: Medium | P12: 3 | R12: =Q12*0.2 -> 0
A13: ELI-012 | B13: FUNC-004 | C13: BP-1765865704672 | D13: PH-01 | E13: DEL-002 | F13: EPIC-013 | H13: Warehouse & Fulfillment | I13: Inventory Management | J13: Manage Inventory | K13: Receive Inventory Into Stock | L13: User Story | M13: As a Warehouse user, I want to receive inventory so newly arrived stock becomes available for allocation. | O13: Medium | P13: 3 | R13: =Q13*0.2 -> 0
A14: ELI-013 | B14: FUNC-005 | C14: BP-1765865704672 | D14: PH-01 | E14: DEL-002 | F14: EPIC-014 | H14: Operations / Order Management | I14: Inventory Management | J14: Track Inventory Availability Across Sources | K14: View Inventory Across Warehouses | L14: User Story | M14: As Ops, I want to see inventory across all warehouses so I can plan multi-location fulfillment. | O14: Medium | P14: 3 | R14: =Q14*0.2 -> 0
A15: ELI-014 | B15: FUNC-005 | C15: BP-1765865704672 | D15: PH-01 | E15: DEL-002 | F15: EPIC-014 | H15: Operations / Order Management | I15: Inventory Management | J15: Track Inventory Availability Across Sources | K15: Include Vendor-Supplied Availability | L15: User Story | M15: As Ops, I want vendor-supplied availability included so out-of-stock items can still be sourced compliantly. | O15: Medium | P15: 3 | R15: =Q15*0.2 -> 0
A16: ELI-015 | B16: FUNC-005 | C16: BP-1765865704672 | D16: PH-01 | E16: DEL-002 | F16: EPIC-014 | H16: Finance / Compliance / Admin | I16: Inventory Management | J16: Track Inventory Availability Across Sources | K16: Distinguish Allocatable vs Informational Stock | L16: User Story | M16: As Finance, I want to distinguish allocatable inventory from informational stock so financial exposure is controlled. | O16: Medium | P16: 3 | R16: =Q16*0.2 -> 0
... A84: ELI-083 | B84: CAP-019 | C84: BP-1765865704672 | D84: PH-01 | E84: DEL-009 | F84: EPIC-009 | H84: N/A | I84: Foundations | J84: DevOps | K84: Automated Testing | L84: Subsystem | M84: Integrate unit, integration, and end-to-end test pipelines. | O84: Medium | P84: 5 | R84: =Q84*0.2 -> 0

Sheet Phase # - Resource Plan
B4: [Solution] Resource Plan
D5: Stage | F5: Validate | G5: Develop | H5: Develop | I5: Develop | J5: Develop | K5: Develop | L5: Develop | M5: Develop | N5: Enable | O5: Enable
B6: Nymbl Resource | C6: Total Hours | D6: Total Amount | E6: Rate | F6: M1 | G6: M2 | H6: M3 | I6: M4 | J6: M5 | K6: M6 | L6: M7 | M6: M8
B7: Strategy Partner | C7: =SUM(F7:AG7) -> 30 | D7: =C7*E7 -> 8250 | E7: 275 | F7: 5 | G7: 5 | H7: 5 | I7: 5 | J7: 5 | K7: 5
B8: Technology Partner | C8: =SUM(F8:AG8) -> 120 | D8: =C8*E8 -> 31200 | E8: 260 | F8: 20 | G8: 20 | H8: 20 | I8: 20 | J8: 20 | K8: 20
B9: Solution Architect | C9: =SUM(F9:AG9) -> 480 | D9: =C9*E9 -> 110400 | E9: 230 | F9: 80 | G9: 80 | H9: 80 | I9: 80 | J9: 80 | K9: 80
B10: Product Designer | C10: =SUM(F10:AG10) -> 160 | D10: =C10*E10 -> 32000 | E10: 200 | F10: 80 | G10: 80
B11: Project Manager | C11: =SUM(F11:AG11) -> 0 | D11: =C11*E11 -> 0 | E11: 190
B12: Lead Developer | C12: =SUM(F12:AG12) -> 480 | D12: =C12*E12 -> 86400 | E12: 180 | G12: 120 | H12: 120 | I12: 120 | J12: 120
B13: Developer | C13: =SUM(F13:AG13) -> 0 | D13: =C13*E13 -> 0 | E13: 175
B14: Developer | C14: =SUM(F14:AG14) -> 0 | D14: =C14*E14 -> 0 | E14: 175
B15: AI Engineer | C15: =SUM(F15:AG15) -> 0 | D15: =C15*E15 -> 0 | E15: 220
B16: Support Engineer | C16: =SUM(F16:AG16) -> 0 | D16: =C16*E16 -> 0 | E16: 190
B17: Cloud Architect | C17: =SUM(F17:AG17) -> 50 | D17: =C17*E17 -> 12000 | E17: 240 | J17: 40 | K17: 10
B18: Quality Assurance Manager | C18: =SUM(F18:AG18) -> 0 | D18: =C18*E18 -> 0 | E18: 130
B19: Documentation Lead | C19: =SUM(F19:AG19) -> 0 | D19: =C19*E19 -> 0 | E19: 150
B20: Total Hours | C20: =SUM(C7:C19) -> 1320 | F20: =SUM(F7:F19) -> 185 | G20: =SUM(G7:G19) -> 305 | H20: =SUM(H7:H19) -> 225 | I20: =SUM(I7:I19) -> 225 | J20: =SUM(J7:J19) -> 265 | K20: =SUM(K7:K19) -> 115 | L20: =SUM(L7:L19) -> 0 | M20: =SUM(M7:M19) -> 0 | ... AG20: =SUM(AG7:AG19) -> 0
B21: Total USD Amount | D21: =SUM(D7:D19) -> 280250 | F21: =SUMPRODUCT($E$7:$E$19,F7:F19) -> 40975 | G21: =SUMPRODUCT($E$7:$E$19,G7:G19) -> 62575 | H21: =SUMPRODUCT($E$7:$E$19,H7:H19) -> 46575 | I21: =SUMPRODUCT($E$7:$E$19,I7:I19) -> 46575 | J21: =SUMPRODUCT($E$7:$E$19,J7:J19) -> 56175 | K21: =SUMPRODUCT($E$7:$E$19,K7:K19) -> 27375 | L21: =SUMPRODUCT($E$7:$E$19,L7:L19) -> 0 | M21: =SUMPRODUCT($E$7:$E$19,M7:M19) -> 0 | ... AG21: =SUMPRODUCT($E$7:$E$19,AG7:AG19) -> 0
C22: Quarter Totals | F22: =sum(F21) -> 40975 | G22: =sum(G21:I21) -> 155725 | J22: =sum(J21:L21) -> 83550 | M22: =sum(M21:O21) -> 0 | P22: =sum(P21:R21) -> 0 | S22: =sum(S21:U21) -> 0 | V22: =sum(V21:X21) -> 0 | Y22: =sum(Y21:AA21) -> 0 | AB22: =sum(AB21:AD21) -> 0 | AE22: =sum(AE21:AG21) -> 0 | AH22: 10% Contigency
C23: Yearly Totals | F23: =sum(F22:I22) -> 196700 | J23: =sum(J22:U22) -> 83550 | V23: =sum(V22:AG22) -> 0
B24: Role Stats
C25: Average Rate | E25: =AVERAGE(E7:E19) -> 201.15385
C26: AVG FTE | F26: =(sum(F7:F19)/180) -> 1.0277778 | G26: =(sum(G7:G19)/180) -> 1.6944444 | H26: =(sum(H7:H19)/180) -> 1.25 | I26: =(sum(I7:I19)/180) -> 1.25 | J26: =(sum(J7:J19)/180) -> 1.4722222 | K26: =(sum(K7:K19)/180) -> 0.63888889 | L26: =(sum(L7:L19)/180) -> 0 | M26: =(sum(M7:M19)/180) -> 0 | ... AG26: =(sum(AG7:AG19)/180) -> 0
B28: [Client] Time Investment
C30: Year | F30: 2025 | J30: 2026 | V30: 2027
C31: Stage | F31: Validate | G31: Build | J31: Enable | K31: Plan | L31: Validate | M31: Build | Q31: Enable | R31: Plan | S31: Validate | T31: Build | W31: Enable | X31: Plan | Y31: Validate | Z31: Build | AC31: Enable
C32: Quarter | F32: Q3 | G32: Q4 | J32: Q1 | M32: Q2 | P32: Q3 | S32: Q4 | V32: Q1 | Y32: Q2 | AB32: Q3 | AE32: Q4
B33: A&M Resource | C33: Total Hours | F33: September | G33: October | H33: November | I33: December | J33: January | K33: February | L33: March | M33: April | N33: May | O33: June | P33: July | Q33: August | R33: September | S33: October | T33: November | U33: December | V33: January | W33: February | X33: March | Y33: April | Z33: May | AA33: June | AB33: July | AC33: August | AD33: September | AE33: October | AF33: November | AG33: December
B34: Stakeholder | C34: =sum(F34:AG34) -> 0
B35: Product Owner | C35: =sum(F35:AG35) -> 0
B36: Subject Matter Experts | C36: =sum(F36:AG36) -> 0
B37: -- Case Management | C37: =sum(F37:AG37) -> 0
B38: -- Reporting and Filing | C38: =sum(F38:AG38) -> 0
B39: Beta Users | C39: =sum(F39:AG39) -> 0
B40: Total Hours | C40: =SUM(C29:C39) -> 0 | F40: =SUM(F34:F39) -> 0 | G40: =SUM(G34:G39) -> 0 | H40: =SUM(H34:H39) -> 0 | I40: =SUM(I34:I39) -> 0 | J40: =SUM(J34:J39) -> 0 | K40: =SUM(K34:K39) -> 0 | L40: =SUM(L34:L39) -> 0 | M40: =SUM(M34:M39) -> 0 | ... AG40: =SUM(AG34:AG39) -> 0
C41: Quarter Totals | F41: =sum(F40) -> 0 | G41: =sum(G40:I40) -> 0 | J41: =sum(J40:L40) -> 0 | M41: =sum(M40:O40) -> 0 | P41: =sum(P40:R40) -> 0 | S41: =sum(S40:U40) -> 0 | V41: =sum(V40:X40) -> 0 | Y41: =sum(Y40:AA40) -> 0 | AB41: =sum(AB40:AD40) -> 0 | AE41: =sum(AE40:AG40) -> 0
C42: Yearly Totals | F42: =sum(F41:I41) -> 0 | J42: =sum(J41:U41) -> 0 | V42: =sum(V41:AG41) -> 0

Sheet Effort Guide
B4: Fibonacci Sequence Definition
B6: Scale | C6: Description
B7: 1 | C7: (Trivial):** Tiny tweak (e.g. typo or label change), virtually no uncertainty.
B8: 2 | C8: (Very Small): Simple story with clear criteria (e.g. add a field), minimal design.
B9: 3 | C9: (Small): Low‑risk work touching a few components (e.g. new API endpoint).
B10: 5 | C10: (Medium): Self‑contained feature in one sprint (e.g. profile editing).
B11: 8 | C11: (Medium–Large): Multi‑scenario story (e.g. onboarding wizard), more testing.
B12: 13 | C12: (Large/Epic Boundary): Epic‑sized but sprint‑length with risk (e.g. checkout flow).
B13: 20 | C13: (Very Large Epic): Multi‑sprint initiative needing breakdown (e.g. billing migration).
B14: 40 | C14: (Huge Initiative): Major multi‑sprint program with dependencies.
B15: 100 | C15: (Monolithic): Placeholder for anything too big—must be decomposed further.

Sheet ROI
B3: Year 1 | C3: Year 2 | D3: Year 3 | G3: Year 1 | H3: Year 2 | I3: Year 3
A4: Order Per Rep | B4: 10 | C4: 15 | D4: 20 | F4: Order Per Rep | G4: 10 | H4: 11 | I4: 12
A5: Orders | B5: =B11*B4 -> 300 | C5: =C11*C4 -> 675 | D5: =D11*D4 -> 1300 | F5: Orders | G5: =G11*G4 -> 300 | H5: =H11*H4 -> 385 | I5: =I11*I4 -> 480
A6: $ per Order | B6: 20000 | C6: 21000 | D6: 22000 | F6: $ per Order | G6: 20000 | H6: 21000 | I6: 22000
A7: Total $ | B7: =B6*B5 -> 6000000 | C7: =C6*C5 -> 14175000 | D7: =D6*D5 -> 28600000 | F7: Total $ | G7: =G6*G5 -> 6000000 | H7: =H6*H5 -> 8085000 | I7: =I6*I5 -> 10560000
A8: Gross Profit % | B8: =0.2 -> 0.2 | C8: 0.21 | D8: 0.22 | F8: Gross Profit % | G8: =0.2 -> 0.2 | H8: 0.21 | I8: 0.22
A9: Total Gross | B9: =B8*B6*B5 -> 1200000 | C9: =C8*C6*C5 -> 2976750 | D9: =D8*D6*D5 -> 6292000 | F9: Total Gross | G9: =G8*G6*G5 -> 1200000 | H9: =H8*H6*H5 -> 1697850 | I9: =I8*I6*I5 -> 2323200
A11: Sales Reps | B11: 30 | C11: 45 | D11: 65 | F11: Sales Reps | G11: 30 | H11: 35 | I11: 40
A12: Sales Rep Commision | B12: =B9*0.1 -> 120000 | C12: =C9*0.1 -> 297675 | D12: =D9*0.1 -> 629200 | F12: Sales Rep Commision | G12: =G9*0.1 -> 120000 | H12: =H9*0.1 -> 169785 | I12: =I9*0.1 -> 232320
A13: Operation HC | B13: =30*60000 -> 1800000 | C13: =B13*1.1 -> 1980000 | D13: =C13*1.1 -> 2178000 | F13: Operation HC | G13: =30*60000 -> 1800000 | H13: =G13*1.1 -> 1980000 | I13: =H13*1.1 -> 2178000
A15: OMS Cost | B15: 300000 | C15: 100000 | D15: 10000 | F15: OMS Cost
A17: Net Profit w OMS | B17: =B9-B12-B13-B15 -> -1020000 | C17: =C9-C12-C13-C15 -> 599075 | D17: =D9-D12-D13-D15 -> 3474800 | F17: Net Profit w/o OMS | G17: =G9-G12-G13-G15 -> -720000 | H17: =H9-H12-H13-H15 -> -451935 | I17: =I9-I12-I13-I15 -> -87120
B20: Year 1 | C20: Year 2 | D20: Year 3 | E20: 3 Year Total
A21: Net Profit w OMS | B21: -1020000 | C21: 599075 | D21: 3474800 | E21: =SUM(B21:D21) -> 3053875
A22: Net Profit w/o OMS | B22: -720000 | C22: -451935 | D22: -87120 | E22: =SUM(B22:D22) -> -1259055
B23: =B21-B22 -> -300000 | C23: =C21-C22 -> 1051010 | D23: =D21-D22 -> 3561920 | E23: =SUM(B23:D23) -> 4312930
